Workbook

Sheet Cover
A1: Asian Paints Ltd (NSE: ASIANPAINT)
A2: Equity Research — Initiation · Financial model
A3: Analyst: Anay Sharma · Student research · Market data as of 17-Sep-2026 · ₹ crore unless stated
A5: MODEL SUMMARY
A6: Rating | B6: =Valuation!B44 -> HOLD | D6: FY26A EPS (₹) | F6: =Historicals!E26 -> 45.093307
A7: Current share price (₹, 17-Sep-2026) | B7: =Assumptions!B33 -> 2454 | D7: FY27E EPS (₹) | F7: =Forecast!D37 -> 53.096451
A8: 12-month target price (₹) | B8: =Valuation!B41 -> 2730 | D8: FY28E EPS (₹) | F8: =Forecast!E37 -> 60.704901
A9: Upside / (downside) | B9: =Valuation!B43 -> 0.11246944 | D9: FY28E P/E at current price | F9: =Valuation!B45 -> 40.425072
A10: DCF value per share (₹, cross-check) | B10: =DCF!B39 -> 1135.1862 | D10: Revenue CAGR FY26A–FY28E | F10: =(Forecast!E15/Forecast!C15)^(1/2)-1 -> 0.11604536
A11: Market-implied perpetual growth | B11: =DCF!B53 -> 0.0914 | D11: FY28E EBITDA margin (excl. OI) | F11: =Forecast!E26 -> 0.195
A13: VALUATION SUMMARY
A14: Method | B14: Key input | C14: Value / share | D14: vs price | E14: Role in the rating
A15: P/E on FY28E EPS (primary) | B15: =TEXT(Assumptions!B32,"0.0")&"x × ₹"&TEXT(Forecast!E37,"0.0") -> 45.0x × ₹60.7 | C15: =Valuation!B41 -> 2730 | D15: =C15/Assumptions!$B$33-1 -> 0.11246944 | E15: Sets the 12-month target
A16: Three-stage DCF (cross-check) | B16: ="WACC "&TEXT(DCF!B14,"0.0%")&", g "&TEXT(DCF!B15,"0.0%") -> WACC 10.9%, g 6.0% | C16: =DCF!B39 -> 1135.1862 | D16: =C16/Assumptions!$B$33-1 -> -0.53741393 | E16: Shows how much long-term growth is already priced in
A17: Scenario-weighted (25/50/25) | B17: Bear / base / bull | C17: =Scenarios!B39 -> 2750 | D17: =C17/Assumptions!$B$33-1 -> 0.1206194 | E17: Checks the skew of outcomes
A19: SCENARIOS — FY28E
A20: Metric | B20: Bear | C20: Base | D20: Bull | E20: What changes
A21: Decorative volume growth (FY28E) | B21: =Scenarios!C6 -> 0.05 | C21: =Scenarios!E6 -> 0.08 | D21: =Scenarios!G6 -> 0.1 | E21: Assumption
A22: Price / mix (FY28E) | B22: =Scenarios!C7 -> -0.01 | C22: =Scenarios!E7 -> 0.01 | D22: =Scenarios!G7 -> 0.02 | E22: Assumption
A23: Gross margin (FY28E) | B23: =Scenarios!C10 -> 0.42 | C23: =Scenarios!E10 -> 0.435 | D23: =Scenarios!G10 -> 0.444 | E23: Assumption
A24: EBITDA margin | B24: =Scenarios!B33 -> 0.176 | C24: =Scenarios!C33 -> 0.195 | D24: =Scenarios!D33 -> 0.209 | E24: Calculated
A25: EPS (₹) | B25: =Scenarios!B34 -> 49.465961 | C25: =Scenarios!C34 -> 60.704901 | D25: =Scenarios!D34 -> 68.54884 | E25: Calculated
A26: Target P/E | B26: =Scenarios!B35 -> 40 | C26: =Scenarios!C35 -> 45 | D26: =Scenarios!D35 -> 52 | E26: Assumption
A27: Target price (₹) | B27: =Scenarios!B36 -> 1980 | C27: =Scenarios!C36 -> 2730 | D27: =Scenarios!D36 -> 3560 | E27: Calculated
A28: Upside / (downside) | B28: =Scenarios!B37 -> -0.19315403 | C28: =Scenarios!C37 -> 0.11246944 | D28: =Scenarios!D37 -> 0.45069275 | E28: Calculated
A30: KEY ASSUMPTIONS — BASE CASE
A31: Assumption | B31: FY26A | C31: FY27E | D31: FY28E | E31: Anchor
A32: Decorative volume growth | B32: =Forecast!C6 -> 0.09 | C32: =Forecast!D6 -> 0.09 | D32: =Forecast!E6 -> 0.08 | E32: Guidance 8–10% for FY27
A33: Price / mix | B33: =Forecast!C7 -> -0.043119266 | C33: =Forecast!D7 -> 0.05 | D33: =Forecast!E7 -> 0.01 | E33: Q1 FY27 +7.0%; value > volume guided
A34: International growth | B34: =Forecast!C10 -> 0.093660318 | C34: =Forecast!D10 -> 0.12 | D34: =Forecast!E10 -> 0.09 | E34: FY26 +9.4%; Q1 FY27 +27%
A35: Industrial growth | B35: =Forecast!C12 -> 0.12372438 | C35: =Forecast!D12 -> 0.14 | D35: =Forecast!E12 -> 0.1 | E35: FY26 +12.4%; 'mid-teens' guided
A36: Gross margin | B36: =Forecast!C19 -> 0.43789235 | C36: =Forecast!D19 -> 0.428 | D36: =Forecast!E19 -> 0.435 | E36: Not guided; Q1 FY27 standalone 43.8%
A37: Employee cost % revenue | B37: =Forecast!C21 -> 0.078676545 | C37: =Forecast!D21 -> 0.075 | D37: =Forecast!E21 -> 0.074 | E37: FY26 7.9%
A38: Other expenses % revenue | B38: =Forecast!C23 -> 0.17104116 | C38: =Forecast!D23 -> 0.166 | D38: =Forecast!E23 -> 0.166 | E38: FY26 17.1%
A39: EBITDA margin (result) | B39: =Forecast!C26 -> 0.18817433 | C39: =Forecast!D26 -> 0.187 | D39: =Forecast!E26 -> 0.195 | E39: Guidance 18–20%
A40: Capex % revenue | B40: =Forecast!C46 -> 0.041227489 | C40: =Forecast!D46 -> 0.045 | D40: =Forecast!E46 -> 0.04 | E40: FY26 4.1%
A41: Tax rate | B41: =Forecast!C33 -> 0.27557234 | C41: =Forecast!D33 -> 0.26 | D41: =Forecast!E33 -> 0.26 | E41: FY24–26: 25–28%
A43: WACC | D43: =DCF!B14 -> 0.10861347 | E43: Calculated in DCF sheet from Assumptions inputs
A44: Terminal growth | D44: =Assumptions!B31 -> 0.06 | E44: Valuation input (Assumptions sheet)
A45: Target P/E on FY28E EPS | D45: =Assumptions!B32 -> 45 | E45: Valuation input (Assumptions sheet)
A47: RESEARCH QUESTION AND ANSWER
A48: Question: can Asian Paints defend margins against Birla Opus while volumes recover — and does the price already pay for that recovery? Answer: the recovery is real (volume 9%, price/mix positive again, EBITDA margin inside guidance), but at ~40x FY28E EPS and a market-implied ~9% perpetual growth rate, the price already assumes it continues. HOLD.
A52: WORKBOOK MAP
A53: Assumptions | B53: Every base-case input in one place: history, guidance, rationale, sensitivity
A54: Historicals | B54: FY23A–FY26A P&L, segments and KPIs; each input row states source, page and verification status
A55: Forecast | B55: Revenue build (volume × price/mix by segment) → P&L → FCFF, with a guidance check
A56: Balance Sheet / Cash Flow | B56: Filed FY24A–FY26A statements; working capital, returns, FCF after leases
A57: Valuation / DCF | B57: Historical P/E band, peers, target multiple, P/E and DCF sensitivities, reverse DCF
A58: Scenarios | B58: Bear / base / bull FY27E–FY28E with target prices
A59: Quarterly Tracker / Driver Tree | B59: Q1 FY26–Q1 FY27 results and guidance; how drivers map into the forecast
A60: Competition / Thesis Breakers | B60: Peer and Birla Opus comparison; thresholds that would prove the view wrong
A61: Checks / Sources | B61: 26 reconciliation and integrity checks; full source log
A63: CONVENTIONS
A64: Blue text | B64: Hard-coded input (historical data from a source, or an assumption)
A65: Black text | B65: Formula
A66: Green text | B66: Link to another sheet
A67: Yellow fill | B67: Key editable assumption
A68: A / E | B68: Actual (reported) / Estimate — estimate headers are shaded slate

Sheet Assumptions
A1: Assumption Log — base case (every forecast input lives here)
A2: Type: G = anchored to management guidance · A = analyst assumption · M = market data · Yellow = key driver
A4: Assumption | B4: FY27E | C4: FY28E | D4: FY29E | E4: FY30E | F4: FY31E | G4: Type | H4: Historical reference | I4: Management guidance | J4: Rationale / source | K4: Sensitivity
A5: REVENUE DRIVERS
A6: Decorative volume growth | B6: 0.09 | C6: 0.08 | D6: 0.08 | E6: 0.075 | F6: 0.07 | G6: G/A | H6: FY24 10%* · FY25 2.5% · FY26 9.0% · Q1FY27 9.0% | I6: FY27: 8–10% (Q1FY27 call) | J6: FY27 = mid-point of guidance and equal to Q1 run-rate. Fades 50bp/yr from FY29 as Birla Opus keeps adding capacity. | K6: ±1pp both years ≈ ±₹1.0 FY28E EPS
A7: Decorative price/mix (realisation) | B7: 0.05 | C7: 0.01 | D7: 0.01 | E7: 0.01 | F7: 0.01 | G7: A | H7: FY24 −5.5% · FY25 −8.0% · FY26 −4.3% · Q1FY27 +7.0% | I7: FY27: value growth to exceed volume | J7: ~10.5–11% cumulative price increases (Q4FY26) help H1; H2 laps them and competition limits further hikes. FY28+: +1% (premium mix offsets discounting). | K7: ±1pp both years ≈ ±₹1.0 FY28E EPS; bear case uses −1% in FY28
A8: International revenue growth (INR) | B8: 0.12 | C8: 0.09 | D8: 0.09 | E8: 0.08 | F8: 0.08 | G8: A | H8: FY26 +9.4% (AR) · Q1FY27 +27.2% | I8: Not guided | J8: Q1 boosted by UAE/Egypt/Nepal; assume moderation. Currency risk in Egypt/Ethiopia/Sri Lanka. | K8: Small: 9% of sales
A9: Industrial revenue growth (AP-PPG) | B9: 0.14 | C9: 0.1 | D9: 0.1 | E9: 0.09 | F9: 0.09 | G9: A | H9: FY26 +12.4% (AR) · Q1FY27 'mid-teens' | I9: 'Mid-teen trajectory' (Q1FY27) | J9: Below Q1 run-rate from FY28; auto/protective coatings capex-linked. | K9: Small: 4% of sales
A10: Other operating revenue (₹ cr) | B10: 67.2 | C10: 67.2 | D10: 67.2 | E10: 67.2 | F10: 67.2 | G10: A | H10: FY26 67.2 · FY25 108.3 | I10: — | J10: Held flat (subsidies/scrap; falling trend). | K10: Negligible
A11: MARGIN DRIVERS
A12: Gross margin (on revenue from ops) | B12: 0.428 | C12: 0.435 | D12: 0.438 | E12: 0.44 | F12: 0.44 | G12: A | H12: FY23 38.7% · FY24 43.4% · FY25 42.4% · FY26 43.8% | I12: Not guided (Q1 standalone 43.8%) | J12: FY27 down ~100bp: crude-linked inputs with Brent ~$105 (Sep-26) and Q1FY27 standalone GM 43.8% vs 45.6% in Q4FY26. Partial recovery from VAE backward integration (Dahej plant producing from 17-Sep-26). | K12: ±100bp GM ≈ ±₹3.4 FY28E EPS
A13: Employee cost % revenue | B13: 0.075 | C13: 0.074 | D13: 0.073 | E13: 0.073 | F13: 0.073 | G13: A | H13: 5.9% → 6.6% → 7.7% → 7.9% (FY23–26) | I13: — | J13: Rose as revenue stalled; operating leverage as revenue grows 14% in FY27. | K13: ±50bp ≈ ±₹1.7 EPS
A14: Other expenses % revenue | B14: 0.166 | C14: 0.166 | D14: 0.167 | E14: 0.168 | F14: 0.168 | G14: A | H14: 14.6% → 15.5% → 17.1% → 17.1% | I14: EBITDA 18–20% (FY27) | J14: Ad-spend and distribution stay elevated while Birla Opus competes; drifts up from FY29. | K14: ±50bp ≈ ±₹1.7 EPS
A15: D&A % revenue | B15: 0.034 | C15: 0.034 | D15: 0.034 | E15: 0.034 | F15: 0.034 | G15: A | H15: 2.5% → 2.4% → 3.0% → 3.5% | I15: — | J15: New plants (Dahej VAE, white cement) keep it near FY26 level. | K15: Minor
A16: Other income % revenue | B16: 0.018 | C16: 0.018 | D16: 0.018 | E16: 0.018 | F16: 0.018 | G16: A | H16: 1.1% → 1.9% → 1.7% → 2.0% | I16: — | J16: Treasury income on ~₹7,000 cr cash & liquid funds. | K16: Minor
A17: Finance costs (₹ cr) | B17: 200 | C17: 200 | D17: 200 | E17: 200 | F17: 200 | G17: A | H17: 144 → 205 → 227 → 195 | I17: — | J17: Mostly lease interest plus new capex borrowing. | K17: Minor
A18: Effective tax rate | B18: 0.26 | C18: 0.26 | D18: 0.26 | E18: 0.26 | F18: 0.26 | G18: A | H18: 26.7% → 24.8% → 28.1% → 27.6% | I18: — | J18: FY25–26 lifted by non-deductible impairments; 26% normalised. | K18: ±1pp ≈ ±₹0.8 EPS
A19: Associates less NCI (₹ cr) | B19: 100 | C19: 100 | D19: 100 | E19: 100 | F19: 100 | G19: A | H19: FY26: +165.6 − 69.3 = 96.3 | I19: — | J19: Held near FY26. | K19: Minor
A20: WORKING CAPITAL & CAPEX
A21: Inventory days (on revenue) | B21: 60 | C21: 60 | D21: 60 | E21: 60 | F21: 60 | G21: A | H21: 65.7 · 60.9 · 72.3 · 58.9 | I21: — | J21: Near FY24/FY26 levels; FY25 spike reversed. | K21: Cash flow only
A22: Receivable days | B22: 46 | C22: 46 | D22: 46 | E22: 46 | F22: 46 | G22: A | H22: 49.1 · 50.3 · 46.4 · 45.8 | I22: — | J22: B2B growth offsets tighter credit. | K22: Cash flow only
A23: Payable days | B23: 40 | C23: 40 | D23: 40 | E23: 40 | F23: 40 | G23: A | H23: 38.5 · 39.4 · 41.4 · 39.6 | I23: — | J23: Stable. | K23: Cash flow only
A24: Capex % revenue | B24: 0.045 | C24: 0.04 | D24: 0.04 | E24: 0.038 | F24: 0.038 | G24: A | H24: PPE capex: 6.2% FY24 · 5.3% FY25 · 4.1% FY26 | I24: — | J24: VAM/VAE ecosystem and white cement in FY27; then maintenance + capacity. | K24: DCF only
A26: VALUATION INPUTS (single value, column B)
A27: Risk-free rate (India 10Y G-sec) | B27: 0.071 | G27: M | H27: — | I27: — | J27: ~7.1% on 15-Sep-2026 (Trading Economics; verify on RBI/CCIL). | K27: See DCF grid
A28: Equity beta | B28: 0.7 | G28: A | H28: — | I28: — | J28: Assumption for a low-beta consumer stock; verify with 2-year weekly beta vs Nifty 50. | K28: ±0.1 beta ≈ ±55bp WACC
A29: Equity risk premium | B29: 0.055 | G29: A | H29: — | I29: — | J29: Within commonly used 5–7% India range. | K29: See DCF grid
A30: Pre-tax cost of debt | B30: 0.075 | G30: A | H30: — | I30: — | J30: AAA-rated (Crisil, Sep-2026). | K30: Negligible (debt ~2% of capital)
A31: Terminal growth | B31: 0.06 | G31: A | H31: — | I31: — | J31: Below India's long-run nominal GDP growth; mature, competitive category. | K31: See DCF grid
A32: Target P/E on FY28E EPS | B32: 45 | G32: A | H32: AP 3-yr median trailing 50x; Berger 43x | I32: — | J32: Derived in Valuation sheet (evidence midpoint 46x, rounded down). | K32: ±5x ≈ ±₹300 target
A33: Current market price (₹) | B33: 2454 | G33: M | H33: — | I33: — | J33: NSE close 17-Sep-2026 (Screener). Update before sending. | K33: —

Sheet Historicals
A1: Asian Paints — Historical Financials (Consolidated, ₹ crore)
A2: FY ends 31 March · Blue = input from source · Black = formula · Green = link · Every input row states its source, page and verification status
B3: ACTUALS
A4: Line item | B4: FY23A | C4: FY24A | D4: FY25A | E4: FY26A | F4: Source (FY24–FY26 unless stated) | G4: Page | H4: Verified | I4: Note
A5: INCOME STATEMENT
A6: Revenue from operations | B6: 34488.59 | C6: 35494.73 | D6: 33905.62 | E6: 35583.54 | F6: IAR FY26 · Consolidated P&L / IAR FY25 · Consolidated P&L | G6: 461 / 442 | H6: Yes (all years) | I6: FY23 = 34,488.6 in Ten-Year Review (p.78–79)
A7: Cost of materials consumed | B7: 17330.58 | C7: 15868.21 | D7: 15793.92 | E7: 15384.05 | F7: IAR FY26 · Consolidated P&L / IAR FY25 · Consolidated P&L | G7: 461 / 442 | H7: FY24–26: Yes | I7: FY23 split from MarketsMojo; FY23 total material cost (row 10) ties to Ten-Year Review
A8: Purchases of stock-in-trade | B8: 4135.65 | C8: 3858.2 | D8: 3926.86 | E8: 4014.05 | F8: IAR FY26 · Consolidated P&L / IAR FY25 · Consolidated P&L | G8: 461 / 442 | H8: FY24–26: Yes
A9: Change in inventories (FG, WIP, stock-in-trade) | B9: -309.73 | C9: 363.8 | D9: -205 | E9: 603.68 | F9: IAR FY26 · Consolidated P&L / IAR FY25 · Consolidated P&L | G9: 461 / 442 | H9: FY24–26: Yes
A10: Total material cost (COGS) | B10: =SUM(B7:B9) -> 21156.5 | C10: =SUM(C7:C9) -> 20090.21 | D10: =SUM(D7:D9) -> 19515.78 | E10: =SUM(E7:E9) -> 20001.78 | F10: IAR FY26 · Ten-Year Review (MD&A) | G10: 78–79 | H10: Yes (all years) | I10: Ten-Year Review: 21,156.5 / 20,090.2 / 19,515.8 / 20,001.8
A11: Gross profit | B11: =B6-B10 -> 13332.09 | C11: =C6-C10 -> 15404.52 | D11: =D6-D10 -> 14389.84 | E11: =E6-E10 -> 15581.76
A12: Employee benefits expense | B12: 2028.07 | C12: 2326.18 | D12: 2597.23 | E12: 2799.59 | F12: IAR FY26 · Consolidated P&L / IAR FY25 · Consolidated P&L | G12: 461 / 442 | H12: FY24–26: Yes | I12: FY23: employee + other (row 13) = 7,072.3 overheads in Ten-Year Review
A13: Other expenses | B13: 5044.18 | C13: 5493.36 | D13: 5786.4 | E13: 6086.25 | F13: IAR FY26 · Consolidated P&L / IAR FY25 · Consolidated P&L | G13: 461 / 442 | H13: FY24–26: Yes | I13: Includes advertising, freight, power. A&P split: see Note 27 (not yet extracted)
A14: EBITDA excl. other income (model definition) | B14: =B11-B12-B13 -> 6259.84 | C14: =C11-C12-C13 -> 7584.98 | D14: =D11-D12-D13 -> 6006.21 | E14: =E11-E12-E13 -> 6695.92 | I14: Company's EBITDA line INCLUDES other income (FY26: 7,419.72). Model uses operating EBITDA excl. other income.
A15: Other income | B15: 386.48 | C15: 687.96 | D15: 572.61 | E15: 723.8 | F15: IAR FY26 · Consolidated P&L / IAR FY25 · Consolidated P&L | G15: 461 / 442 | H15: FY24–26: Yes
A16: Finance costs | B16: 144.45 | C16: 205.17 | D16: 227.02 | E16: 195.41 | F16: IAR FY26 · Consolidated P&L / IAR FY25 · Consolidated P&L | G16: 461 / 442 | H16: Yes (all years)
A17: Depreciation & amortisation | B17: 858.02 | C17: 853 | D17: 1026.34 | E17: 1228.85 | F17: IAR FY26 · Consolidated P&L / IAR FY25 · Consolidated P&L | G17: 461 / 442 | H17: Yes (all years)
A18: Exceptional items | B18: -48.87 | C18: 0 | D18: -363.1 | E18: -157.61 | F18: IAR FY26 · Consolidated P&L / IAR FY25 · Consolidated P&L | G18: 461 / 442 | H18: Yes (all years) | I18: FY25: goodwill/intangible impairment (White Teak, Causeway) + Indonesia exit; FY26: White Teak impairment + Labour Code
A19: PBT (before share of associates) | B19: =B14+B15-B16-B17+B18 -> 5594.98 | C19: =C14+C15-C16-C17+C18 -> 7214.77 | D19: =D14+D15-D16-D17+D18 -> 4962.36 | E19: =E14+E15-E16-E17+E18 -> 5837.85 | I19: Company PBT includes associates: FY26 6,003.44 = this row + row 22 (see Checks)
A20: Tax expense | B20: 1493.5 | C20: 1790.08 | D20: 1393.36 | E20: 1608.75 | F20: IAR FY26 · Consolidated P&L / IAR FY25 · Consolidated P&L | G20: 461 / 442 | H20: FY24–26: Yes
A21: PAT before associates & minority | B21: =B19-B20 -> 4101.48 | C21: =C19-C20 -> 5424.69 | D21: =D19-D20 -> 3569 | E21: =E19-E20 -> 4229.1
A22: Share of profit of associates | B22: 93.85 | C22: 133 | D22: 140.71 | E22: 165.59 | F22: IAR FY26 · Consolidated P&L / IAR FY25 · Consolidated P&L | G22: 461 / 442 | H22: FY24–26: Yes | I22: Mainly PPG Asian Paints (PPGAP), an associate — its revenue is NOT in consolidated sales
A23: Non-controlling interest | B23: -88.88 | C23: -97.46 | D23: -42.48 | E23: -69.34 | F23: IAR FY26 · Consolidated P&L / IAR FY25 · Consolidated P&L | G23: 461 / 442 | H23: FY24–26: Yes
A24: Net profit attributable to owners | B24: =B21+B22+B23 -> 4106.45 | C24: =C21+C22+C23 -> 5460.23 | D24: =D21+D22+D23 -> 3667.23 | E24: =E21+E22+E23 -> 4325.35 | F24: IAR FY26 · Ten-Year Review (MD&A) | G24: 78–79 | H24: Yes (all years) | I24: 4,106.5 / 5,460.2 / 3,667.2 / 4,325.3
A25: Shares outstanding (crore) | B25: 95.92 | C25: 95.92 | D25: 95.92 | E25: 95.92 | F25: IAR FY26 · Consolidated Balance Sheet | G25: 459 | H25: Yes | I25: Equity capital ₹95.92 cr, FV ₹1
A26: EPS — model (₹, NP ÷ 95.92 cr shares) | B26: =B24/B25 -> 42.811197 | C26: =C24/C25 -> 56.924833 | D26: =D24/D25 -> 38.232173 | E26: =E24/E25 -> 45.093307
A27: EPS — company-reported basic (₹) | B27: 42.8 | C27: 56.95 | D27: 38.25 | E27: 45.12 | F27: IAR FY26 · Consolidated P&L / IAR FY25 · Consolidated P&L | G27: 461 / 443 | H27: Yes | I27: Company uses weighted shares net of ESOP-trust treasury shares, so reported EPS is ~₹0.03 higher. FY23 from Ten-Year Review (1 decimal).
A29: MARGINS & GROWTH
A30: Revenue growth | C30: =C6/B6-1 -> 0.029173127 | D30: =D6/C6-1 -> -0.044770308 | E30: =E6/D6-1 -> 0.049487961
A31: Gross margin (on revenue from operations) | B31: =B11/B6 -> 0.38656524 | C31: =C11/C6 -> 0.43399457 | D31: =D11/D6 -> 0.4244087 | E31: =E11/E6 -> 0.43789235
A32: EBITDA margin (excl. other income) | B32: =B14/B6 -> 0.18150467 | C32: =C14/C6 -> 0.21369313 | D32: =D14/D6 -> 0.17714497 | E32: =E14/E6 -> 0.18817464
A33: Net margin (owners) | B33: =B24/B6 -> 0.11906691 | C33: =C24/C6 -> 0.15383213 | D33: =D24/D6 -> 0.10815995 | E33: =E24/E6 -> 0.1215548
A34: Effective tax rate | B34: =B20/B19 -> 0.26693572 | C34: =C20/C19 -> 0.24811325 | D34: =D20/D19 -> 0.28078576 | E34: =E20/E19 -> 0.27557234
A35: Employee cost % revenue | B35: =B12/B6 -> 0.058804086 | C35: =C12/C6 -> 0.065535926 | D35: =D12/D6 -> 0.076601755 | E35: =E12/E6 -> 0.078676545
A36: Other expenses % revenue | B36: =B13/B6 -> 0.14625649 | C36: =C13/C6 -> 0.15476551 | D36: =D13/D6 -> 0.17066197 | E36: =E13/E6 -> 0.17104116
A37: Net profit growth | C37: =C24/B24-1 -> 0.32967161 | D37: =D24/C24-1 -> -0.32837445 | E37: =E24/D24-1 -> 0.1794597
A39: SEGMENT REVENUE (company-reported, sale of products & services)
A40: Decorative & home décor | D40: 29545.3 | E40: 30830.4 | F40: IAR FY26 · Financial Review (MD&A) | G40: 60–61 | H40: Yes | I40: 86.8% of FY26 sales. FY23–24 segment split: not yet extracted (FY24/FY23 AR)
A41: International | D41: 3066.4 | E41: 3353.6 | F41: IAR FY26 · Financial Review (MD&A) | G41: 60–61 | H41: Yes | I41: Results release showed 3,339.7 for FY26 — small definitional gap vs AR segment table; AR used
A42: Industrial (AP-PPG only; PPGAP is an associate) | D42: 1185.7 | E42: 1332.4 | F42: IAR FY26 · Financial Review (MD&A) | G42: 60–61 | H42: Yes | I42: IAR FY25 notes industrial revenue excludes PPGAP (associate)
A43: Consolidated net sales (company) | B43: 34367.8 | C43: 35382.1 | D43: 33797.4 | E43: 35516.4 | F43: IAR FY26 · Ten-Year Review (MD&A) | G43: 78–79 | H43: Yes
A44: Segment total (check vs row 43) | D44: =SUM(D40:D42) -> 33797.4 | E44: =SUM(E40:E42) -> 35516.4
A45: Other operating revenue | B45: 120.8 | C45: 112.6 | D45: 108.3 | E45: 67.2 | F45: IAR FY26 · Ten-Year Review (MD&A) | G45: 78–79 | H45: Yes | I45: Net sales + other operating revenue = revenue from operations
A47: OPERATING KPIs
A48: Standalone net sales | B48: 29953.1 | C48: 31093.8 | D48: 29421.1 | E48: 30680.2 | F48: IAR FY26 · Ten-Year Review (MD&A) | G48: 78–79 | H48: Yes | I48: FY24 restated (Sleek, Maxbhumi amalgamation); FY25 restated (APPPL). Original FY24 release: 30,727.7
A49: Decorative India volume growth | C49: 0.1 | D49: 0.025 | E49: 0.09 | F49: Results releases via PCI Mag / Quartr / GuruFocus | G49: n/a | H49: Partial | I49: FY24 = Decorative + Industrial combined (only combined disclosed). Verify against Q4 releases.
A50: Decorative India value growth | C50: 0.039 | D50: -0.057 | E50: 0.043 | F50: As above | G50: n/a | H50: Partial
A51: Implied price/mix (realisation) | C51: =(1+C50)/(1+C49)-1 -> -0.055454545 | D51: =(1+D50)/(1+D49)-1 -> -0.08 | E51: =(1+E50)/(1+E49)-1 -> -0.043119266 | I51: Derived: (1+value)/(1+volume)−1. Company does not disclose price/mix directly.
A52: Company-reported gross margin (% of net sales) | B52: 0.384 | C52: 0.432 | D52: 0.423 | E52: 0.437 | F52: IAR FY26 · Ten-Year Review (MD&A) | G52: 78–79 | H52: Yes | I52: Company computes on net sales; model row 31 uses revenue from ops
A53: Company-reported ROCE (consolidated) | B53: 0.359 | C53: 0.397 | D53: 0.269 | E53: 0.276 | F53: IAR FY26 · Ten-Year Review (MD&A) | G53: 78–79 | H53: Yes | I53: Includes other income; model ROCE (BS sheet) excludes it
A54: Company-reported return on net worth | B54: 0.274 | C54: 0.31 | D54: 0.188 | E54: 0.209 | F54: IAR FY26 · Ten-Year Review (MD&A) | G54: 78–79 | H54: Yes
A55: Market capitalisation at 31 March (₹ cr) | B55: 264897 | C55: 273060 | D55: 224232 | E55: 207618 | F55: IAR FY26 · Ten-Year Review (MD&A) | G55: 78–79 | H55: Yes | I55: Used for historical P/E in Valuation sheet

Sheet Forecast
A1: Driver-Based Forecast — FY25A to FY31E (₹ crore)
A2: Decorative revenue = prior year × (1 + volume) × (1 + price/mix). All inputs pulled from the Assumptions sheet. Column I says what each row is.
B3: HISTORICAL | D3: FORECAST
A4: Line item | B4: FY25A | C4: FY26A | D4: FY27E | E4: FY28E | F4: FY29E | G4: FY30E | H4: FY31E | I4: Row type
A5: REVENUE BUILD
A6: Decorative volume growth | B6: =Historicals!D49 -> 0.025 | C6: =Historicals!E49 -> 0.09 | D6: =Assumptions!B6 -> 0.09 | E6: =Assumptions!C6 -> 0.08 | F6: =Assumptions!D6 -> 0.08 | G6: =Assumptions!E6 -> 0.075 | H6: =Assumptions!F6 -> 0.07 | I6: Hist: fact · Fcst: assumption (guided)
A7: Price/mix (realisation) | B7: =Historicals!D51 -> -0.08 | C7: =Historicals!E51 -> -0.043119266 | D7: =Assumptions!B7 -> 0.05 | E7: =Assumptions!C7 -> 0.01 | F7: =Assumptions!D7 -> 0.01 | G7: =Assumptions!E7 -> 0.01 | H7: =Assumptions!F7 -> 0.01 | I7: Hist: derived fact · Fcst: assumption
A8: Decorative & home décor growth | C8: =Historicals!E40/Historicals!D40-1 -> 0.04349592 | D8: =(1+D6)*(1+D7)-1 -> 0.1445 | E8: =(1+E6)*(1+E7)-1 -> 0.0908 | F8: =(1+F6)*(1+F7)-1 -> 0.0908 | G8: =(1+G6)*(1+G7)-1 -> 0.08575 | H8: =(1+H6)*(1+H7)-1 -> 0.0807 | I8: Calculated = (1+vol)×(1+price/mix)−1
A9: Decorative & home décor revenue | B9: =Historicals!D40 -> 29545.3 | C9: =Historicals!E40 -> 30830.4 | D9: =C9*(1+D8) -> 35285.393 | E9: =D9*(1+E8) -> 38489.306 | F9: =E9*(1+F8) -> 41984.135 | G9: =F9*(1+G8) -> 45584.275 | H9: =G9*(1+H8) -> 49262.926 | I9: Calculated
A10: International growth | C10: =Historicals!E41/Historicals!D41-1 -> 0.093660318 | D10: =Assumptions!B8 -> 0.12 | E10: =Assumptions!C8 -> 0.09 | F10: =Assumptions!D8 -> 0.09 | G10: =Assumptions!E8 -> 0.08 | H10: =Assumptions!F8 -> 0.08 | I10: Assumption
A11: International revenue | B11: =Historicals!D41 -> 3066.4 | C11: =Historicals!E41 -> 3353.6 | D11: =C11*(1+D10) -> 3756.032 | E11: =D11*(1+E10) -> 4094.0749 | F11: =E11*(1+F10) -> 4462.5416 | G11: =F11*(1+G10) -> 4819.5449 | H11: =G11*(1+H10) -> 5205.1085 | I11: Calculated
A12: Industrial growth | C12: =Historicals!E42/Historicals!D42-1 -> 0.12372438 | D12: =Assumptions!B9 -> 0.14 | E12: =Assumptions!C9 -> 0.1 | F12: =Assumptions!D9 -> 0.1 | G12: =Assumptions!E9 -> 0.09 | H12: =Assumptions!F9 -> 0.09 | I12: Assumption (guided 'mid-teens')
A13: Industrial revenue | B13: =Historicals!D42 -> 1185.7 | C13: =Historicals!E42 -> 1332.4 | D13: =C13*(1+D12) -> 1518.936 | E13: =D13*(1+E12) -> 1670.8296 | F13: =E13*(1+F12) -> 1837.9126 | G13: =F13*(1+G12) -> 2003.3247 | H13: =G13*(1+H12) -> 2183.6239 | I13: Calculated
A14: Other operating revenue | B14: =Historicals!D45 -> 108.3 | C14: =Historicals!E45 -> 67.2 | D14: =Assumptions!B10 -> 67.2 | E14: =Assumptions!C10 -> 67.2 | F14: =Assumptions!D10 -> 67.2 | G14: =Assumptions!E10 -> 67.2 | H14: =Assumptions!F10 -> 67.2 | I14: Assumption
A15: Revenue from operations | B15: =B9+B11+B13+B14 -> 33905.7 | C15: =C9+C11+C13+C14 -> 35583.6 | D15: =D9+D11+D13+D14 -> 40627.561 | E15: =E9+E11+E13+E14 -> 44321.411 | F15: =F9+F11+F13+F14 -> 48351.79 | G15: =G9+G11+G13+G14 -> 52474.345 | H15: =H9+H11+H13+H14 -> 56718.859 | I15: Calculated (FY25–26 tie to filings — see Checks)
A16: Revenue growth | C16: =C15/B15-1 -> 0.049487254 | D16: =D15/C15-1 -> 0.14174959 | E16: =E15/D15-1 -> 0.090919811 | F16: =F15/E15-1 -> 0.090935253 | G16: =G15/F15-1 -> 0.085261685 | H16: =H15/G15-1 -> 0.08088741 | I16: Calculated
A18: PROFIT & LOSS
A19: Gross margin | B19: =Historicals!D31 -> 0.4244087 | C19: =Historicals!E31 -> 0.43789235 | D19: =Assumptions!B12 -> 0.428 | E19: =Assumptions!C12 -> 0.435 | F19: =Assumptions!D12 -> 0.438 | G19: =Assumptions!E12 -> 0.44 | H19: =Assumptions!F12 -> 0.44 | I19: Assumption (not guided)
A20: Gross profit | B20: =Historicals!D11 -> 14389.84 | C20: =Historicals!E11 -> 15581.76 | D20: =D15*D19 -> 17388.596 | E20: =E15*E19 -> 19279.814 | F20: =F15*F19 -> 21178.084 | G20: =G15*G19 -> 23088.712 | H20: =H15*H19 -> 24956.298 | I20: Calculated
A21: Employee cost % revenue | B21: =Historicals!D35 -> 0.076601755 | C21: =Historicals!E35 -> 0.078676545 | D21: =Assumptions!B13 -> 0.075 | E21: =Assumptions!C13 -> 0.074 | F21: =Assumptions!D13 -> 0.073 | G21: =Assumptions!E13 -> 0.073 | H21: =Assumptions!F13 -> 0.073 | I21: Assumption
A22: Employee cost | B22: =Historicals!D12 -> 2597.23 | C22: =Historicals!E12 -> 2799.59 | D22: =D15*D21 -> 3047.0671 | E22: =E15*E21 -> 3279.7844 | F22: =F15*F21 -> 3529.6806 | G22: =G15*G21 -> 3830.6272 | H22: =H15*H21 -> 4140.4767 | I22: Calculated
A23: Other expenses % revenue | B23: =Historicals!D36 -> 0.17066197 | C23: =Historicals!E36 -> 0.17104116 | D23: =Assumptions!B14 -> 0.166 | E23: =Assumptions!C14 -> 0.166 | F23: =Assumptions!D14 -> 0.167 | G23: =Assumptions!E14 -> 0.168 | H23: =Assumptions!F14 -> 0.168 | I23: Assumption
A24: Other expenses | B24: =Historicals!D13 -> 5786.4 | C24: =Historicals!E13 -> 6086.25 | D24: =D15*D23 -> 6744.1751 | E24: =E15*E23 -> 7357.3542 | F24: =F15*F23 -> 8074.7489 | G24: =G15*G23 -> 8815.6899 | H24: =H15*H23 -> 9528.7682 | I24: Calculated
A25: EBITDA (excl. other income) | B25: =B20-B22-B24 -> 6006.21 | C25: =C20-C22-C24 -> 6695.92 | D25: =D20-D22-D24 -> 7597.3539 | E25: =E20-E22-E24 -> 8642.6751 | F25: =F20-F22-F24 -> 9573.6544 | G25: =G20-G22-G24 -> 10442.395 | H25: =H20-H22-H24 -> 11287.053 | I25: Calculated
A26: EBITDA margin | B26: =B25/B15 -> 0.17714455 | C26: =C25/C15 -> 0.18817433 | D26: =D25/D15 -> 0.187 | E26: =E25/E15 -> 0.195 | F26: =F25/F15 -> 0.198 | G26: =G25/G15 -> 0.199 | H26: =H25/H15 -> 0.199 | I26: Calculated · guidance 18–20%
A27: D&A % revenue | B27: =Historicals!D17/Historicals!D6 -> 0.030270498 | C27: =Historicals!E17/Historicals!E6 -> 0.034534226 | D27: =Assumptions!B15 -> 0.034 | E27: =Assumptions!C15 -> 0.034 | F27: =Assumptions!D15 -> 0.034 | G27: =Assumptions!E15 -> 0.034 | H27: =Assumptions!F15 -> 0.034 | I27: Assumption
A28: D&A | B28: =Historicals!D17 -> 1026.34 | C28: =Historicals!E17 -> 1228.85 | D28: =D15*D27 -> 1381.3371 | E28: =E15*E27 -> 1506.928 | F28: =F15*F27 -> 1643.9608 | G28: =G15*G27 -> 1784.1277 | H28: =H15*H27 -> 1928.4412 | I28: Calculated
A29: EBIT | B29: =B25-B28 -> 4979.87 | C29: =C25-C28 -> 5467.07 | D29: =D25-D28 -> 6216.0168 | E29: =E25-E28 -> 7135.7472 | F29: =F25-F28 -> 7929.6935 | G29: =G25-G28 -> 8658.2669 | H29: =H25-H28 -> 9358.6117 | I29: Calculated
A30: Other income | B30: =Historicals!D15 -> 572.61 | C30: =Historicals!E15 -> 723.8 | D30: =D15*Assumptions!B16 -> 731.29609 | E30: =E15*Assumptions!C16 -> 797.7854 | F30: =F15*Assumptions!D16 -> 870.33221 | G30: =G15*Assumptions!E16 -> 944.53821 | H30: =H15*Assumptions!F16 -> 1020.9395 | I30: Calculated from assumption
A31: Finance costs | B31: =Historicals!D16 -> 227.02 | C31: =Historicals!E16 -> 195.41 | D31: =Assumptions!B17 -> 200 | E31: =Assumptions!C17 -> 200 | F31: =Assumptions!D17 -> 200 | G31: =Assumptions!E17 -> 200 | H31: =Assumptions!F17 -> 200 | I31: Assumption
A32: PBT before exceptional items & associates | B32: =Historicals!D19-Historicals!D18 -> 5325.46 | C32: =Historicals!E19-Historicals!E18 -> 5995.46 | D32: =D29+D30-D31 -> 6747.3129 | E32: =E29+E30-E31 -> 7733.5326 | F32: =F29+F30-F31 -> 8600.0257 | G32: =G29+G30-G31 -> 9402.8051 | H32: =H29+H30-H31 -> 10179.551 | I32: Calculated (no exceptionals forecast)
A33: Tax rate | B33: =Historicals!D34 -> 0.28078576 | C33: =Historicals!E34 -> 0.27557234 | D33: =Assumptions!B18 -> 0.26 | E33: =Assumptions!C18 -> 0.26 | F33: =Assumptions!D18 -> 0.26 | G33: =Assumptions!E18 -> 0.26 | H33: =Assumptions!F18 -> 0.26 | I33: Assumption
A34: PAT before associates & NCI | D34: =D32*(1-D33) -> 4993.0115 | E34: =E32*(1-E33) -> 5722.8141 | F34: =F32*(1-F33) -> 6364.019 | G34: =G32*(1-G33) -> 6958.0758 | H34: =H32*(1-H33) -> 7532.8678 | I34: Calculated
A35: Associates less NCI | B35: =Historicals!D22+Historicals!D23 -> 98.23 | C35: =Historicals!E22+Historicals!E23 -> 96.25 | D35: =Assumptions!B19 -> 100 | E35: =Assumptions!C19 -> 100 | F35: =Assumptions!D19 -> 100 | G35: =Assumptions!E19 -> 100 | H35: =Assumptions!F19 -> 100 | I35: Assumption
A36: Net profit to owners | B36: =Historicals!D24 -> 3667.23 | C36: =Historicals!E24 -> 4325.35 | D36: =D34+D35 -> 5093.0115 | E36: =E34+E35 -> 5822.8141 | F36: =F34+F35 -> 6464.019 | G36: =G34+G35 -> 7058.0758 | H36: =H34+H35 -> 7632.8678 | I36: Calculated · FY25–26 after exceptionals
A37: EPS (₹) | B37: =Historicals!D26 -> 38.232173 | C37: =Historicals!E26 -> 45.093307 | D37: =D36/Historicals!$E$25 -> 53.096451 | E37: =E36/Historicals!$E$25 -> 60.704901 | F37: =F36/Historicals!$E$25 -> 67.38969 | G37: =G36/Historicals!$E$25 -> 73.582942 | H37: =H36/Historicals!$E$25 -> 79.575353 | I37: Calculated
A38: EPS growth | C38: =C37/B37-1 -> 0.1794597 | D38: =D37/C37-1 -> 0.17747964 | E38: =E37/D37-1 -> 0.14329489 | F38: =F37/E37-1 -> 0.11011942 | G38: =G37/F37-1 -> 0.091902071 | H38: =H37/G37-1 -> 0.081437502 | I38: FY27 flattered: FY26 had ₹158 cr exceptional charges
A40: WORKING CAPITAL & CAPEX
A41: Inventory days | B41: ='Balance Sheet'!D29 -> 72.334131 | C41: ='Balance Sheet'!E29 -> 58.916197 | D41: =Assumptions!B21 -> 60 | E41: =Assumptions!C21 -> 60 | F41: =Assumptions!D21 -> 60 | G41: =Assumptions!E21 -> 60 | H41: =Assumptions!F21 -> 60 | I41: Assumption
A42: Receivable days | B42: ='Balance Sheet'!D30 -> 46.437206 | C42: ='Balance Sheet'!E30 -> 45.767144 | D42: =Assumptions!B22 -> 46 | E42: =Assumptions!C22 -> 46 | F42: =Assumptions!D22 -> 46 | G42: =Assumptions!E22 -> 46 | H42: =Assumptions!F22 -> 46 | I42: Assumption
A43: Payable days | B43: ='Balance Sheet'!D31 -> 41.424401 | C43: ='Balance Sheet'!E31 -> 39.625332 | D43: =Assumptions!B23 -> 40 | E43: =Assumptions!C23 -> 40 | F43: =Assumptions!D23 -> 40 | G43: =Assumptions!E23 -> 40 | H43: =Assumptions!F23 -> 40 | I43: Assumption
A44: Trade working capital | B44: ='Balance Sheet'!D32 -> 7184.92 | C44: ='Balance Sheet'!E32 -> 6342.45 | D44: =D15*(D41+D42-D43)/365 -> 7346.3535 | E44: =E15*(E41+E42-E43)/365 -> 8014.2825 | F44: =F15*(F41+F42-F43)/365 -> 8743.0633 | G44: =G15*(G41+G42-G43)/365 -> 9488.5117 | H44: =H15*(H41+H42-H43)/365 -> 10256.013 | I44: Calculated
A45: Increase in working capital | D45: =D44-C44 -> 1003.9035 | E45: =E44-D44 -> 667.92907 | F45: =F44-E44 -> 728.78081 | G45: =G44-F44 -> 745.44832 | H45: =H44-G44 -> 767.50113 | I45: Calculated
A46: Capex % revenue | B46: ='Cash Flow'!D17 -> 0.05324545 | C46: ='Cash Flow'!E17 -> 0.041227489 | D46: =Assumptions!B24 -> 0.045 | E46: =Assumptions!C24 -> 0.04 | F46: =Assumptions!D24 -> 0.04 | G46: =Assumptions!E24 -> 0.038 | H46: =Assumptions!F24 -> 0.038 | I46: Assumption
A47: Capex | B47: ='Cash Flow'!D6 -> 1805.32 | C47: ='Cash Flow'!E6 -> 1467.02 | D47: =D15*D46 -> 1828.2402 | E47: =E15*E46 -> 1772.8564 | F47: =F15*F46 -> 1934.0716 | G47: =G15*G46 -> 1994.0251 | H47: =H15*H46 -> 2155.3166 | I47: Calculated
A49: FREE CASH FLOW TO FIRM
A50: NOPAT = EBIT × (1 − tax) | D50: =D29*(1-D33) -> 4599.8524 | E50: =E29*(1-E33) -> 5280.4529 | F50: =F29*(1-F33) -> 5867.9732 | G50: =G29*(1-G33) -> 6407.1175 | H50: =H29*(1-H33) -> 6925.3726
A51: + D&A | D51: =D28 -> 1381.3371 | E51: =E28 -> 1506.928 | F51: =F28 -> 1643.9608 | G51: =G28 -> 1784.1277 | H51: =H28 -> 1928.4412
A52: − Capex | D52: =D47 -> 1828.2402 | E52: =E47 -> 1772.8564 | F52: =F47 -> 1934.0716 | G52: =G47 -> 1994.0251 | H52: =H47 -> 2155.3166
A53: − Increase in working capital | D53: =D45 -> 1003.9035 | E53: =E45 -> 667.92907 | F53: =F45 -> 728.78081 | G53: =G45 -> 745.44832 | H53: =H45 -> 767.50113
A54: FCFF | D54: =D50+D51-D52-D53 -> 3149.0458 | E54: =E50+E51-E52-E53 -> 4346.5954 | F54: =F50+F51-F52-F53 -> 4849.0816 | G54: =G50+G51-G52-G53 -> 5451.7718 | H54: =H50+H51-H52-H53 -> 5930.9961 | I54: Calculated (pre-lease; leases treated as debt in EV bridge)
A55: FCFF margin | D55: =D54/D15 -> 0.077510088 | E55: =E54/E15 -> 0.098069878 | F55: =F54/F15 -> 0.10028753 | G55: =G54/G15 -> 0.10389404 | H55: =H54/H15 -> 0.10456833
A56: Reinvestment rate | D56: =(D52-D51+D53)/D50 -> 0.31540286 | E56: =(E52-E51+E53)/E50 -> 0.17685179 | F56: =(F52-F51+F53)/F50 -> 0.17363603 | G56: =(G52-G51+G53)/G50 -> 0.14910694 | H56: =(H52-H51+H53)/H50 -> 0.14358456 | I56: (Capex − D&A + ΔWC) / NOPAT
A58: GUIDANCE CHECK (does the model stay inside what management has said?)
A59: FY27 decorative volume inside 8–10% guidance? | D59: =IF(AND(D6>=0.08,D6<=0.1),"Inside","OUTSIDE") -> Inside
A60: EBITDA margin inside 18–20% guidance? | D60: =IF(AND(D26>=0.18,D26<=0.2),"Inside","OUTSIDE") -> Inside | E60: =IF(AND(E26>=0.18,E26<=0.2),"Inside","OUTSIDE") -> Inside | F60: =IF(AND(F26>=0.18,F26<=0.2),"Inside","OUTSIDE") -> Inside | G60: =IF(AND(G26>=0.18,G26<=0.2),"Inside","OUTSIDE") -> Inside | H60: =IF(AND(H26>=0.18,H26<=0.2),"Inside","OUTSIDE") -> Inside
A61: FY27 value growth above volume growth (as guided)? | D61: =IF(D8>D6,"Yes","NO") -> Yes

Sheet Balance Sheet
A1: Balance Sheet, Working Capital & Returns (Consolidated, ₹ crore)
A2: As at 31 March · FY24–FY26 from audited balance sheets; FY23 partly from aggregator (flagged)
B3: ACTUALS
A4: Line item | B4: FY23A | C4: FY24A | D4: FY25A | E4: FY26A | F4: Source | G4: Page | H4: Verified | I4: Note
A5: EQUITY & LIABILITIES
A6: Equity share capital | B6: 95.92 | C6: 95.92 | D6: 95.92 | E6: 95.92 | F6: IAR FY26 · Consolidated Balance Sheet / IAR FY25 · Consolidated Balance Sheet | G6: 459 / 440 | H6: Yes
A7: Other equity | B7: 15896.31 | C7: 18632.38 | D7: 19303.89 | E7: 21275.67 | F7: IAR FY26 · Consolidated Balance Sheet / IAR FY25 · Consolidated Balance Sheet | G7: 459 / 440 | H7: Yes | I7: FY23 also in Ten-Year Review (15,896.3)
A8: Equity attributable to owners | B8: =B6+B7 -> 15992.23 | C8: =C6+C7 -> 18728.3 | D8: =D6+D7 -> 19399.81 | E8: =E6+E7 -> 21371.59
A9: Non-controlling interests | B9: 453.66 | C9: 695.38 | D9: 659.24 | E9: 643.39 | F9: IAR FY26 · Consolidated Balance Sheet / IAR FY25 · Consolidated Balance Sheet | G9: 459 / 440 | H9: FY24–26: Yes | I9: FY23 from IAR FY25 statement of changes in equity (453.66)
A10: Borrowings (non-current + current) | B10: 972.21 | C10: 1107.14 | D10: 863.75 | E10: 2293.26 | F10: IAR FY26 · Consolidated Balance Sheet / IAR FY25 · Consolidated Balance Sheet; FY23: IAR FY25 CF reconciliation | G10: 459 / 440 / 448 | H10: Yes (all years) | I10: FY26 rise funds capex (company note to debt-equity ratio)
A11: Lease liabilities (non-current + current) | B11: 960.41 | C11: 1367.24 | D11: 1426.54 | E11: 1635.67 | F11: IAR FY26 · Consolidated Balance Sheet / IAR FY25 · Consolidated Balance Sheet; FY23: IAR FY25 CF reconciliation | G11: 459 / 440 / 448 | H11: Yes (all years) | I11: v1 derived these from Screener (e.g. FY26 1,635.74); replaced with filed figures
A12: Total debt incl. leases | B12: =B10+B11 -> 1932.62 | C12: =C10+C11 -> 2474.38 | D12: =D10+D11 -> 2290.29 | E12: =E10+E11 -> 3928.93
A13: Trade payables | B13: 3635.44 | C13: 3831.34 | D13: 3848 | E13: 3863.04 | F13: IAR FY26 · Consolidated Balance Sheet / IAR FY25 · Consolidated Balance Sheet | G13: 459 / 440 | H13: FY24–26: Yes; FY23: No | I13: FY23 from MarketsMojo — verify in IAR FY24
A14: ASSETS
A15: Property, plant & equipment (excl. ROU) | C15: 4446.2 | D15: 6787.62 | E15: 7146.23 | F15: IAR FY26 · Consolidated Balance Sheet / IAR FY25 · Consolidated Balance Sheet | G15: 459 / 440 | H15: Yes | I15: FY23: not yet extracted
A16: Right-of-use assets | C16: 1856.27 | D16: 1843.72 | E16: 2018.77 | F16: IAR FY26 · Consolidated Balance Sheet / IAR FY25 · Consolidated Balance Sheet | G16: 459 / 440 | H16: Yes
A17: Capital work-in-progress | B17: 1019.59 | C17: 2698.37 | D17: 1254.49 | E17: 1848.67 | F17: IAR FY26 · Consolidated Balance Sheet / IAR FY25 · Consolidated Balance Sheet | G17: 459 / 440 | H17: FY24–26: Yes; FY23: No
A18: Non-current investments (incl. associates) | B18: 1564.71 | C18: 1384.51 | D18: 1479.79 | E18: 775.91 | F18: IAR FY26 · Consolidated Balance Sheet / IAR FY25 · Consolidated Balance Sheet | G18: 459 / 440 | H18: FY24–26: Yes; FY23: No | I18: FY26 fall: sale of Akzo Nobel India stake (₹923 cr proceeds)
A19: of which: investments in associates | C19: 583.13 | D19: 608 | E19: 656.09 | F19: IAR FY26 · Consolidated Balance Sheet / IAR FY25 · Consolidated Balance Sheet | G19: 459 / 440 | H19: Yes | I19: Not cash — valued at book in the DCF bridge
A20: Current investments (mainly liquid funds) | B20: 2697 | C20: 3203.41 | D20: 3244.96 | E20: 6285.83 | F20: IAR FY26 · Consolidated Balance Sheet / IAR FY25 · Consolidated Balance Sheet | G20: 459 / 440 | H20: FY24–26: Yes; FY23: No
A21: Inventories | B21: 6210.64 | C21: 5923.41 | D21: 6719.27 | E21: 5743.69 | F21: IAR FY26 · Consolidated Balance Sheet / IAR FY25 · Consolidated Balance Sheet | G21: 459 / 440 | H21: FY24–26: Yes; FY23: No
A22: Trade receivables (current) | B22: 4636.94 | C22: 4889.05 | D22: 4313.65 | E22: 4461.8 | F22: IAR FY26 · Consolidated Balance Sheet / IAR FY25 · Consolidated Balance Sheet | G22: 459 / 440 | H22: FY24–26: Yes; FY23: No
A23: Cash & equivalents + other bank balances | B23: 843.82 | C23: 1084.01 | D23: 781.98 | E23: 1073.68 | F23: IAR FY26 · Consolidated Balance Sheet / IAR FY25 · Consolidated Balance Sheet | G23: 459 / 440 | H23: FY24–26: Yes; FY23: No | I23: FY26: 672.83 + 400.85. Term deposits in 'other financial assets' are NOT included (conservative)
A24: Total assets (reported) | B24: 25779.33 | C24: 29924.09 | D24: 30371.37 | E24: 34534.49 | F24: IAR FY26 · Consolidated Balance Sheet / IAR FY25 · Consolidated Balance Sheet | G24: 459 / 440 | H24: FY24–26: Yes; FY23: No | I24: CORRECTED: v1 used aggregator totals (e.g. FY26 34,518.75) that netted tax balances
A26: WORKING CAPITAL
A27: Revenue from operations | B27: =Historicals!B6 -> 34488.59 | C27: =Historicals!C6 -> 35494.73 | D27: =Historicals!D6 -> 33905.62 | E27: =Historicals!E6 -> 35583.54
A28: Total material cost | B28: =Historicals!B10 -> 21156.5 | C28: =Historicals!C10 -> 20090.21 | D28: =Historicals!D10 -> 19515.78 | E28: =Historicals!E10 -> 20001.78
A29: Inventory days (on revenue) | B29: =B21/B27*365 -> 65.728509 | C29: =C21/C27*365 -> 60.911709 | D29: =D21/D27*365 -> 72.334131 | E29: =E21/E27*365 -> 58.916197
A30: Receivable days (on revenue) | B30: =B22/B27*365 -> 49.073711 | C30: =C22/C27*365 -> 50.275161 | D30: =D22/D27*365 -> 46.437206 | E30: =E22/E27*365 -> 45.767144
A31: Payable days (on revenue) | B31: =B13/B27*365 -> 38.474626 | C31: =C13/C27*365 -> 39.398499 | D31: =D13/D27*365 -> 41.424401 | E31: =E13/E27*365 -> 39.625332
A32: Trade working capital (Inv + Rec − Pay) | B32: =B21+B22-B13 -> 7212.14 | C32: =C21+C22-C13 -> 6981.12 | D32: =D21+D22-D13 -> 7184.92 | E32: =E21+E22-E13 -> 6342.45
A33: Trade working capital days | B33: =B32/B27*365 -> 76.327594 | C33: =C32/C27*365 -> 71.78837 | D33: =D32/D27*365 -> 77.346935 | E33: =E32/E27*365 -> 65.058009
A34: Inventory days on material cost (memo) | B34: =B21/B28*365 -> 107.14833 | C34: =C21/C28*365 -> 107.61683 | D34: =D21/D28*365 -> 125.66926 | E34: =E21/E28*365 -> 104.81301 | I34: Company-reported inventory turnover on COGS: 3.2x FY26, 3.1x FY25 (Financial Review p.60)
A36: RETURNS & LEVERAGE
A37: EBIT (EBITDA excl. OI − D&A) | B37: =Historicals!B14-Historicals!B17 -> 5401.82 | C37: =Historicals!C14-Historicals!C17 -> 6731.98 | D37: =Historicals!D14-Historicals!D17 -> 4979.87 | E37: =Historicals!E14-Historicals!E17 -> 5467.07
A38: Capital employed (equity + NCI + debt incl. leases) | B38: =B8+B9+B12 -> 18378.51 | C38: =C8+C9+C12 -> 21898.06 | D38: =D8+D9+D12 -> 22349.34 | E38: =E8+E9+E12 -> 25943.91
A39: ROE (on average equity) | C39: =Historicals!C24/AVERAGE(B8:C8) -> 0.31452458 | D39: =Historicals!D24/AVERAGE(C8:D8) -> 0.19236359 | E39: =Historicals!E24/AVERAGE(D8:E8) -> 0.21217569
A40: ROCE (EBIT excl. OI / avg capital employed) | C40: =C37/AVERAGE(B38:C38) -> 0.33428765 | D40: =D37/AVERAGE(C38:D38) -> 0.2250921 | E40: =E37/AVERAGE(D38:E38) -> 0.22641135 | I40: Stricter than company ROCE (27.6% FY26), which includes other income
A41: Cash + investments (incl. associates at book) | B41: =B18+B20+B23 -> 5105.53 | C41: =C18+C20+C23 -> 5671.93 | D41: =D18+D20+D23 -> 5506.73 | E41: =E18+E20+E23 -> 8135.42
A42: Net debt / (net cash) incl. leases | B42: =B12-B41 -> -3172.91 | C42: =C12-C41 -> -3197.55 | D42: =D12-D41 -> -3216.44 | E42: =E12-E41 -> -4206.49
A43: Debt incl. leases / equity | B43: =B12/B8 -> 0.12084744 | C43: =C12/C8 -> 0.13211984 | D43: =D12/D8 -> 0.11805734 | E43: =E12/E8 -> 0.18383892
A44: Book value per share (₹) | B44: =B8/Historicals!B25 -> 166.72467 | C44: =C8/Historicals!C25 -> 195.24917 | D44: =D8/Historicals!D25 -> 202.2499 | E44: =E8/Historicals!E25 -> 222.8064 | F44: IAR FY26 · Ten-Year Review (MD&A) | G44: 78–79 | H44: Check | I44: Company: 166.7 / 195.2 / 202.2 / 222.8

Sheet Cash Flow
A1: Cash Flow Analysis (Consolidated, ₹ crore)
A2: FY24–FY26 from audited cash flow statements; FY23 from aggregator (flagged)
B3: ACTUALS
A4: Line item | B4: FY23A | C4: FY24A | D4: FY25A | E4: FY26A | F4: Source | G4: Page | H4: Verified | I4: Note
A5: Cash from operating activities (CFO) | B5: 4193 | C5: 6103.6 | D5: 4423.96 | E5: 7088.18 | F5: IAR FY26 · Consolidated Cash Flow / IAR FY25 · Consolidated Cash Flow | G5: 465 / 446 | H5: FY24–26: Yes; FY23: No | I5: FY23 from Screener
A6: Capex: purchase of PPE & intangibles | B6: 1419 | C6: 2199.01 | D6: 1805.32 | E6: 1467.02 | F6: IAR FY26 · Consolidated Cash Flow / IAR FY25 · Consolidated Cash Flow | G6: 465 / 446–447 | H6: FY24–26: Yes; FY23: No | I6: FY23 = Screener CFO − FCF (includes ROU payments) — not like-for-like
A7: Payments for right-of-use assets | C7: 297.07 | D7: 24.75 | E7: 20.3 | F7: IAR FY26 · Consolidated Cash Flow / IAR FY25 · Consolidated Cash Flow | G7: 465 / 446–447 | H7: Yes
A8: Cash from investing activities | B8: -1282 | C8: -2517.63 | D8: -874.12 | E8: -1334.07 | F8: IAR FY26 · Consolidated Cash Flow / IAR FY25 · Consolidated Cash Flow | G8: 465 / 447 | H8: FY24–26: Yes; FY23: No | I8: CORRECTED: Screener showed −2,548 / −941 / −1,328
A9: Cash from financing activities | B9: -2140 | C9: -2982.5 | D9: -3752.58 | E9: -2376.51 | F9: IAR FY26 · Consolidated Cash Flow / IAR FY25 · Consolidated Cash Flow | G9: 466 / 447 | H9: FY24–26: Yes; FY23: No
A10: Net change in cash (CFO + CFI + CFF) | B10: =SUM(B5,B8,B9) -> 771 | C10: =SUM(C5,C8,C9) -> 603.47 | D10: =SUM(D5,D8,D9) -> -202.74 | E10: =SUM(E5,E8,E9) -> 3377.6
A11: Free cash flow (CFO − PPE capex) | B11: =B5-B6 -> 2774 | C11: =C5-C6 -> 3904.59 | D11: =D5-D6 -> 2618.64 | E11: =E5-E6 -> 5621.16
A12: Lease principal repaid | C12: 285.63 | D12: 324.62 | E12: 339.78 | F12: IAR FY26 · Consolidated Cash Flow / IAR FY25 · Consolidated Cash Flow | G12: 466 / 447 | H12: Yes
A13: FCF after lease payments | C13: =C11-C12 -> 3618.96 | D13: =D11-D12 -> 2294.02 | E13: =E11-E12 -> 5281.38 | I13: Stricter FCF: leases are an operating cost of the store/depot network
A14: Dividends paid (incl. to NCI) | C14: 2550.88 | D14: 3140.21 | E14: 2425.38 | F14: IAR FY26 · Consolidated Cash Flow / IAR FY25 · Consolidated Cash Flow | G14: 466 / 447 | H14: Yes | I14: FY25 higher because FY24 final (₹28.15) paid in FY25
A15: CFO / EBITDA (excl. OI) | B15: =B5/Historicals!B14 -> 0.66982543 | C15: =C5/Historicals!C14 -> 0.8046956 | D15: =D5/Historicals!D14 -> 0.73656432 | E15: =E5/Historicals!E14 -> 1.0585819
A16: FCF / net profit | B16: =B11/Historicals!B24 -> 0.67552265 | C16: =C11/Historicals!C24 -> 0.71509625 | D16: =D11/Historicals!D24 -> 0.71406484 | E16: =E11/Historicals!E24 -> 1.299585
A17: Capex / revenue | B17: =B6/Historicals!B6 -> 0.041144042 | C17: =C6/Historicals!C6 -> 0.061953141 | D17: =D6/Historicals!D6 -> 0.05324545 | E17: =E6/Historicals!E6 -> 0.041227489
A18: Capex / D&A | B18: =B6/Historicals!B17 -> 1.6538076 | C18: =C6/Historicals!C17 -> 2.5779719 | D18: =D6/Historicals!D17 -> 1.7589882 | E18: =E6/Historicals!E17 -> 1.1938154
A19: Dividend per share (₹) | B19: 25.65 | C19: 33.3 | D19: 24.8 | E19: 27.5 | F19: IAR FY26 · Ten-Year Review (MD&A) | G19: 78–79 | H19: Yes | I19: From dividend % on ₹1 face value: 2565% / 3330% / 2480% / 2750%
A20: Dividend payout (DPS / reported EPS) | B20: =B19/Historicals!B27 -> 0.59929907 | C20: =C19/Historicals!C27 -> 0.58472344 | D20: =D19/Historicals!D27 -> 0.64836601 | E20: =E19/Historicals!E27 -> 0.60948582 | F20: IAR FY26 · Ten-Year Review (MD&A) | G20: 78–79 | H20: Check | I20: Company payout policy 60% (before exceptional items)
A21: Company-reported net change in cash (for Checks) | C21: 603.47 | D21: -202.74 | E21: 3377.6 | F21: IAR FY26 · Consolidated Cash Flow / IAR FY25 · Consolidated Cash Flow | G21: 466 / 447 | H21: Yes

Sheet Valuation
A1: Valuation — P/E framework, peers, target price and sensitivities
A2: Primary method: P/E on FY28E EPS. Cross-check: DCF / reverse DCF (DCF sheet)
A4: A. ASIAN PAINTS HISTORICAL P/E — from company year-end market cap (Ten-Year Review)
A5: Year-end | B5: Market cap (₹ cr) | C5: PAT, same FY | D5: Trailing P/E | E5: PAT, next FY | F5: 1-yr fwd P/E (realised)
A6: 31-Mar-2022 | B6: 295428 | C6: 3030.6 | D6: =B6/C6 -> 97.481687 | E6: =Historicals!B24 -> 4106.45 | F6: =B6/E6 -> 71.942432 | H6: FY22 market cap & PAT: Ten-Year Review p.78–79
A7: 31-Mar-2023 | B7: =Historicals!B55 -> 264897 | C7: =Historicals!B24 -> 4106.45 | D7: =B7/C7 -> 64.507543 | E7: =Historicals!C24 -> 5460.23 | F7: =B7/E7 -> 48.51389
A8: 31-Mar-2024 | B8: =Historicals!C55 -> 273060 | C8: =Historicals!C24 -> 5460.23 | D8: =B8/C8 -> 50.008882 | E8: =Historicals!D24 -> 3667.23 | F8: =B8/E8 -> 74.459469
A9: 31-Mar-2025 | B9: =Historicals!D55 -> 224232 | C9: =Historicals!D24 -> 3667.23 | D9: =B9/C9 -> 61.144788 | E9: =Historicals!E24 -> 4325.35 | F9: =B9/E9 -> 51.841354
A10: 31-Mar-2026 | B10: =Historicals!E55 -> 207618 | C10: =Historicals!E24 -> 4325.35 | D10: =B10/C10 -> 48.000277
A11: 3-yr average / median trailing (FY24–26) | B11: =AVERAGE(D8:D10) -> 53.051316 | C11: =MEDIAN(D8:D10) -> 50.008882
A12: 5-yr average / median trailing (FY22–26) | B12: =AVERAGE(D6:D10) -> 64.228635 | C12: =MEDIAN(D6:D10) -> 61.144788
A13: 3-yr average / median 1-yr forward (Mar-23 to Mar-25) | B13: =AVERAGE(F7:F9) -> 58.271571 | C13: =MEDIAN(F7:F9) -> 51.841354
A14: 4-yr average / median 1-yr forward (Mar-22 to Mar-25) | B14: =AVERAGE(F6:F9) -> 61.689286 | C14: =MEDIAN(F6:F9) -> 61.891893
A15: Columns B/C in rows 11–14 = average / median. Limitation: five year-end snapshots, not daily averages; FY22 and FY25 multiples are inflated by earnings dips. A daily-price series from NSE would give a more robust band.
A17: B. PEER COMPARISON (market data mid-Sep-2026; TTM = four quarters to Jun-2026)
A18: Company | B18: Mkt cap | C18: FY26 revenue | D18: FY25 revenue | E18: FY26 rev growth | F18: Q1FY27 rev growth | G18: TTM EBITDA | H18: TTM revenue | I18: TTM EBITDA margin | J18: Borrowings | K18: Investments | L18: EV | M18: EV / EBITDA | N18: P/E (TTM) | O18: ROCE | P18: ROE
A19: Asian Paints | B19: =DCF!B11 -> 235387.68 | C19: =Historicals!E6 -> 35583.54 | D19: =Historicals!D6 -> 33905.62 | E19: =C19/D19-1 -> 0.049487961 | F19: ='Quarterly Tracker'!F7 -> 0.179 | G19: =Historicals!E14-'Quarterly Tracker'!B6*'Quarterly Tracker'!B13+'Quarterly Tracker'!F6*'Quarterly Tracker'!F13 -> 7240.6534 | H19: =Historicals!E6-'Quarterly Tracker'!B6+'Quarterly Tracker'!F6 -> 37186.44 | I19: =G19/H19 -> 0.1947122 | J19: ='Balance Sheet'!E12 -> 3928.93 | K19: ='Balance Sheet'!E18+'Balance Sheet'!E20 -> 7061.74 | L19: =B19+J19-K19 -> 232254.87 | M19: =L19/G19 -> 32.076507 | N19: =Assumptions!B33/((Historicals!E24-'Quarterly Tracker'!B14+'Quarterly Tracker'!F14)/Historicals!E25) -> 49.402932 | O19: 0.263 | P19: 0.218
A20: Berger Paints | B20: 52558 | C20: 11880 | D20: 11545 | E20: =C20/D20-1 -> 0.02901689 | F20: =3584/3201-1 -> 0.11965011 | G20: 1912 | H20: 12263 | I20: =G20/H20 -> 0.15591617 | J20: 635 | K20: 1189 | L20: =B20+J20-K20 -> 52004 | M20: =L20/G20 -> 27.198745 | N20: 42.8 | O20: 0.216 | P20: 0.173
A21: Kansai Nerolac | B21: 14866 | C21: 8052 | D21: 7823 | E21: =C21/D21-1 -> 0.029272658 | F21: =2374/2162-1 -> 0.098057354 | G21: 1000 | H21: 8263 | I21: =G21/H21 -> 0.12102142 | J21: 303 | K21: 2365 | L21: =B21+J21-K21 -> 12804 | M21: =L21/G21 -> 12.804 | N21: 23.1 | O21: 0.12 | P21: 0.0882
A22: Indigo Paints (standalone) | B22: 5196 | C22: 1330 | D22: 1277 | E22: =C22/D22-1 -> 0.041503524 | F22: =350/295-1 -> 0.18644068 | G22: 265 | H22: 1385 | I22: =G22/H22 -> 0.19133574 | J22: 18 | K22: 320 | L22: =B22+J22-K22 -> 4894 | M22: =L22/G22 -> 18.467925 | N22: 31.4 | O22: 0.179 | P22: 0.134
A23: Median of listed peers (ex-Asian Paints) | E23: =MEDIAN(E20:E22) -> 0.029272658 | F23: =MEDIAN(F20:F22) -> 0.11965011 | I23: =MEDIAN(I20:I22) -> 0.15591617 | M23: =MEDIAN(M20:M22) -> 18.467925 | N23: =MEDIAN(N20:N22) -> 31.4 | O23: =MEDIAN(O20:O22) -> 0.179 | P23: =MEDIAN(P20:P22) -> 0.134
A24: Sources: Screener.in (Berger, Kansai consolidated; Indigo standalone), 17–18 Sep 2026 — aggregator, verify against each company's filings. EV = market cap + borrowings − investments (bank cash excluded for all, so EVs are slightly high). ROCE/ROE for all four are Screener figures for like-for-like comparison (Asian Paints' own reported ROCE is 27.6%). Forward consensus EPS for peers was not accessed, so peer forward P/Es are NOT shown. Birla Opus is not separately listed.
A26: C. HOW THE TARGET MULTIPLE IS DERIVED
A27: Asian Paints 3-yr median trailing P/E (year-end) | B27: =C11 -> 50.008882
A28: Asian Paints current trailing P/E (CMP / TTM EPS) | B28: =N19 -> 49.402932
A29: Berger Paints current trailing P/E | B29: =N20 -> 42.8
A30: Evidence midpoint = average(AP 3-yr median, Berger) | B30: =AVERAGE(B27,B29) -> 46.404441
A31: Selected multiple (Assumptions) | B31: =Assumptions!B32 -> 45
A32: Selected minus midpoint | B32: =B31-B30 -> -1.4044412
A33: Why a premium to Berger: faster growth (FY26 revenue +4.9% vs +2.9%; Q1FY27 +17.9% vs +12.0%), higher returns (ROCE 26.3% vs 21.6%), higher EBITDA margin (19.5% vs 15.6% TTM) and ~3x the revenue scale.
A34: Why a discount to Asian Paints' own history: returns have stepped down (company ROCE 39.7% FY24 → 27.6% FY26) and Birla Opus (~10% revenue share, ~24% of capacity) makes FY24-level margins unlikely to return.
A35: Rounding: midpoint rounded DOWN to 45x rather than up, because FY27 gross margin is under crude-linked pressure (Q1FY27 standalone GM 43.8% vs 45.6% in Q4FY26).
A36: Applied to FY28E EPS because a 12-month target (Sep-2027) sits inside FY28; FY27E would include the one-off benefit of lapping FY26 exceptional charges.
A38: D. TARGET PRICE AND WHAT THE CURRENT PRICE IMPLIES
A39: FY28E EPS (₹) | B39: =Forecast!E37 -> 60.704901
A40: Target P/E | B40: =B31 -> 45
A41: 12-month target price (₹) | B41: =ROUND(B39*B40,-1) -> 2730
A42: Current market price (₹) | B42: =Assumptions!B33 -> 2454
A43: Upside / (downside) | B43: =B41/B42-1 -> 0.11246944
A44: Rating (BUY > +15%, SELL < −10%, else HOLD) | B44: =IF(B43>0.15,"BUY",IF(B43<-0.1,"SELL","HOLD")) -> HOLD
A45: Implied FY28E P/E at current price | B45: =B42/B39 -> 40.425072
A46: Price at which upside would exceed 15% (₹) | B46: =B41/1.15 -> 2373.913
A47: → implied FY28E P/E at that price | B47: =B46/B39 -> 39.105789
A48: Price at which downside would exceed 10% (₹) | B48: =B41/0.9 -> 3033.3333
A49: → implied FY28E P/E at that price | B49: =B48/B39 -> 49.968508
A51: E. SENSITIVITY — target price (₹): FY28E EPS (rows) × P/E (columns)
A52: FY28E EPS ↓ / P/E → | B52: 40 | C52: 42.5 | D52: 45 | E52: 47.5 | F52: 50 | G52: 52 | H52: Shaded = at or above current price; outlined = base case
A53: =$B$39*(1+-0.1) -> 54.634411 | B53: =ROUND($A53*B$52,-1) -> 2190 | C53: =ROUND($A53*C$52,-1) -> 2320 | D53: =ROUND($A53*D$52,-1) -> 2460 | E53: =ROUND($A53*E$52,-1) -> 2600 | F53: =ROUND($A53*F$52,-1) -> 2730 | G53: =ROUND($A53*G$52,-1) -> 2840 | H53: -10% vs base EPS
A54: =$B$39*(1+-0.05) -> 57.669656 | B54: =ROUND($A54*B$52,-1) -> 2310 | C54: =ROUND($A54*C$52,-1) -> 2450 | D54: =ROUND($A54*D$52,-1) -> 2600 | E54: =ROUND($A54*E$52,-1) -> 2740 | F54: =ROUND($A54*F$52,-1) -> 2880 | G54: =ROUND($A54*G$52,-1) -> 3000 | H54: -5% vs base EPS
A55: =$B$39*(1+0) -> 60.704901 | B55: =ROUND($A55*B$52,-1) -> 2430 | C55: =ROUND($A55*C$52,-1) -> 2580 | D55: =ROUND($A55*D$52,-1) -> 2730 | E55: =ROUND($A55*E$52,-1) -> 2880 | F55: =ROUND($A55*F$52,-1) -> 3040 | G55: =ROUND($A55*G$52,-1) -> 3160 | H55: +0% vs base EPS
A56: =$B$39*(1+0.05) -> 63.740146 | B56: =ROUND($A56*B$52,-1) -> 2550 | C56: =ROUND($A56*C$52,-1) -> 2710 | D56: =ROUND($A56*D$52,-1) -> 2870 | E56: =ROUND($A56*E$52,-1) -> 3030 | F56: =ROUND($A56*F$52,-1) -> 3190 | G56: =ROUND($A56*G$52,-1) -> 3310 | H56: +5% vs base EPS
A57: =$B$39*(1+0.1) -> 66.775391 | B57: =ROUND($A57*B$52,-1) -> 2670 | C57: =ROUND($A57*C$52,-1) -> 2840 | D57: =ROUND($A57*D$52,-1) -> 3000 | E57: =ROUND($A57*E$52,-1) -> 3170 | F57: =ROUND($A57*F$52,-1) -> 3340 | G57: =ROUND($A57*G$52,-1) -> 3470 | H57: +10% vs base EPS
A59: F. WHY P/E AND DCF GIVE DIFFERENT ANSWERS
A60: P/E asks: what will investors pay for next year's earnings? It embeds the market's own long-run assumptions without stating them, and moves mainly with EPS revisions and sentiment. ±5x on the multiple moves the target by ~₹300.
A61: DCF asks: what are the cash flows worth at an explicit discount rate? With a ~10.9% WACC and 6% terminal growth, 15 years of forecast cash flows are worth ~₹1,130/share. It is dominated by the gap between WACC and terminal growth: cutting WACC by 1pp and raising terminal growth by 1pp lifts the value by roughly half.
A62: The gap is the finding, not a mistake: at today's price the market is implying ~9% perpetual growth at a ~10.9% WACC (or an ~8.2% WACC at 6% growth) — i.e. it treats Asian Paints as a very long-duration compounder.
A63: How we use it: P/E sets the 12-month target because that is how the stock is priced; the DCF shows how little margin of safety there is if long-term growth or the multiple disappoints. That asymmetry is why the rating stops at HOLD.

Sheet DCF
A1: Discounted Cash Flow — three-stage (cross-check to P/E)
A2: Stage 1: FY27–FY31 driver forecast · Stage 2: FY32–FY41 growth fades linearly to terminal rate · Stage 3: Gordon terminal value
A4: COST OF CAPITAL (inputs linked from Assumptions)
A5: Risk-free rate | B5: =Assumptions!B27 -> 0.071
A6: Equity beta | B6: =Assumptions!B28 -> 0.7
A7: Equity risk premium | B7: =Assumptions!B29 -> 0.055
A8: Cost of equity (CAPM) | B8: =B5+B6*B7 -> 0.1095
A9: Pre-tax cost of debt | B9: =Assumptions!B30 -> 0.075
A10: Tax rate | B10: =Forecast!D33 -> 0.26
A11: Market capitalisation (₹ cr) | B11: =B34*Historicals!E25 -> 235387.68
A12: Debt incl. leases (₹ cr) | B12: ='Balance Sheet'!E12 -> 3928.93
A13: Weight of debt | B13: =B12/(B12+B11) -> 0.016417289
A14: WACC | B14: =(1-B13)*B8+B13*B9*(1-B10) -> 0.10861347
A15: Terminal growth | B15: =Assumptions!B31 -> 0.06
A17: CASH FLOW SCHEDULE (₹ cr)
C18: FY27E | D18: FY28E | E18: FY29E | F18: FY30E | G18: FY31E | H18: FY32E | I18: FY33E | J18: FY34E | K18: FY35E | L18: FY36E | M18: FY37E | N18: FY38E | O18: FY39E | P18: FY40E | Q18: FY41E
A19: Stage | C19: Stage 1 | D19: Stage 1 | E19: Stage 1 | F19: Stage 1 | G19: Stage 1 | H19: Stage 2 | I19: Stage 2 | J19: Stage 2 | K19: Stage 2 | L19: Stage 2 | M19: Stage 2 | N19: Stage 2 | O19: Stage 2 | P19: Stage 2 | Q19: Stage 2
A20: Revenue growth | C20: =Forecast!D16 -> 0.14174959 | D20: =Forecast!E16 -> 0.090919811 | E20: =Forecast!F16 -> 0.090935253 | F20: =Forecast!G16 -> 0.085261685 | G20: =Forecast!H16 -> 0.08088741 | H20: =$G$20-($G$20-$B$15)*1/10 -> 0.078798669 | I20: =$G$20-($G$20-$B$15)*2/10 -> 0.076709928 | J20: =$G$20-($G$20-$B$15)*3/10 -> 0.074621187 | K20: =$G$20-($G$20-$B$15)*4/10 -> 0.072532446 | L20: =$G$20-($G$20-$B$15)*5/10 -> 0.070443705 | M20: =$G$20-($G$20-$B$15)*6/10 -> 0.068354964 | N20: =$G$20-($G$20-$B$15)*7/10 -> 0.066266223 | O20: =$G$20-($G$20-$B$15)*8/10 -> 0.064177482 | P20: =$G$20-($G$20-$B$15)*9/10 -> 0.062088741 | Q20: =$G$20-($G$20-$B$15)*10/10 -> 0.06
A21: Revenue | C21: =Forecast!D15 -> 40627.561 | D21: =Forecast!E15 -> 44321.411 | E21: =Forecast!F15 -> 48351.79 | F21: =Forecast!G15 -> 52474.345 | G21: =Forecast!H15 -> 56718.859 | H21: =G21*(1+H20) -> 61188.229 | I21: =H21*(1+I20) -> 65881.974 | J21: =I21*(1+J20) -> 70798.165 | K21: =J21*(1+K20) -> 75933.329 | L21: =K21*(1+L20) -> 81282.354 | M21: =L21*(1+M20) -> 86838.406 | N21: =M21*(1+N20) -> 92592.859 | O21: =N21*(1+O20) -> 98535.236 | ... Q21: =P21*(1+Q20) -> 110932.35
A22: EBITDA margin | C22: =Forecast!D26 -> 0.187 | D22: =Forecast!E26 -> 0.195 | E22: =Forecast!F26 -> 0.198 | F22: =Forecast!G26 -> 0.199 | G22: =Forecast!H26 -> 0.199 | H22: =$G$22 -> 0.199 | I22: =$G$22 -> 0.199 | J22: =$G$22 -> 0.199 | K22: =$G$22 -> 0.199 | L22: =$G$22 -> 0.199 | M22: =$G$22 -> 0.199 | N22: =$G$22 -> 0.199 | O22: =$G$22 -> 0.199 | ... Q22: =$G$22 -> 0.199
A23: FCFF | C23: =Forecast!D54 -> 3149.0458 | D23: =Forecast!E54 -> 4346.5954 | E23: =Forecast!F54 -> 4849.0816 | F23: =Forecast!G54 -> 5451.7718 | G23: =Forecast!H54 -> 5930.9961 | H23: =(H21*H22-H21*Forecast!$H$27)*(1-Forecast!$H$33)+H21*Forecast!$H$27-H21*Forecast!$H$46-(H21-G21)*(Forecast!$H$41+Forecast!$H$42-Forecast!$H$43)/365 -> 6418.1697 | I23: =(I21*I22-I21*Forecast!$H$27)*(1-Forecast!$H$33)+I21*Forecast!$H$27-I21*Forecast!$H$46-(I21-H21)*(Forecast!$H$41+Forecast!$H$42-Forecast!$H$43)/365 -> 6931.9292 | J23: =(J21*J22-J21*Forecast!$H$27)*(1-Forecast!$H$33)+J21*Forecast!$H$27-J21*Forecast!$H$46-(J21-I21)*(Forecast!$H$41+Forecast!$H$42-Forecast!$H$43)/365 -> 7472.3082 | K23: =(K21*K22-K21*Forecast!$H$27)*(1-Forecast!$H$33)+K21*Forecast!$H$27-K21*Forecast!$H$46-(K21-J21)*(Forecast!$H$41+Forecast!$H$42-Forecast!$H$43)/365 -> 8039.1759 | L23: =(L21*L22-L21*Forecast!$H$27)*(1-Forecast!$H$33)+L21*Forecast!$H$27-L21*Forecast!$H$46-(L21-K21)*(Forecast!$H$41+Forecast!$H$42-Forecast!$H$43)/365 -> 8632.225 | M23: =(M21*M22-M21*Forecast!$H$27)*(1-Forecast!$H$33)+M21*Forecast!$H$27-M21*Forecast!$H$46-(M21-L21)*(Forecast!$H$41+Forecast!$H$42-Forecast!$H$43)/365 -> 9250.9597 | N23: =(N21*N22-N21*Forecast!$H$27)*(1-Forecast!$H$33)+N21*Forecast!$H$27-N21*Forecast!$H$46-(N21-M21)*(Forecast!$H$41+Forecast!$H$42-Forecast!$H$43)/365 -> 9894.6854 | O23: =(O21*O22-O21*Forecast!$H$27)*(1-Forecast!$H$33)+O21*Forecast!$H$27-O21*Forecast!$H$46-(O21-N21)*(Forecast!$H$41+Forecast!$H$42-Forecast!$H$43)/365 -> 10562.499 | ... Q23: =(Q21*Q22-Q21*Forecast!$H$27)*(1-Forecast!$H$33)+Q21*Forecast!$H$27-Q21*Forecast!$H$46-(Q21-P21)*(Forecast!$H$41+Forecast!$H$42-Forecast!$H$43)/365 -> 11965.696
A24: Discount period (mid-year, from 31-Mar-2026) | C24: 0.5 | D24: 1.5 | E24: 2.5 | F24: 3.5 | G24: 4.5 | H24: 5.5 | I24: 6.5 | J24: 7.5 | K24: 8.5 | L24: 9.5 | M24: 10.5 | N24: 11.5 | O24: 12.5 | P24: 13.5 | Q24: 14.5
A25: Discount factor | C25: =1/(1+$B$14)^C24 -> 0.94975136 | D25: =1/(1+$B$14)^D24 -> 0.85670199 | E25: =1/(1+$B$14)^E24 -> 0.77276888 | F25: =1/(1+$B$14)^F24 -> 0.6970589 | G25: =1/(1+$B$14)^G24 -> 0.6287664 | H25: =1/(1+$B$14)^H24 -> 0.56716468 | I25: =1/(1+$B$14)^I24 -> 0.51159822 | J25: =1/(1+$B$14)^J24 -> 0.46147574 | ... Q25: =1/(1+$B$14)^Q24 -> 0.22422696
A26: PV of FCFF | C26: =C23*C25 -> 2990.8105 | D26: =D23*D25 -> 3723.7369 | E26: =E23*E25 -> 3747.2194 | F26: =F23*F25 -> 3800.206 | G26: =G23*G25 -> 3729.2111 | H26: =H23*H25 -> 3640.1592 | I26: =I23*I25 -> 3546.3627 | J26: =J23*J25 -> 3448.289 | ... Q26: =Q23*Q25 -> 2683.0316
A28: VALUATION
A29: Sum of PV of FCFF (FY27–FY41) | B29: =SUM(C26:Q26) -> 49761.052
A30: Terminal value at end-FY41 | B30: =Q23*(1+B15)/(B14-B15) -> 260907.91
A31: PV of terminal value | B31: =B30/(1+B14)^15 -> 55562.911
A32: Enterprise value | B32: =B29+B31 -> 105323.96
A33: Terminal value as % of EV | B33: =B31/B32 -> 0.52754292
A34: Current market price (₹) | B34: =Assumptions!B33 -> 2454
A35: + Cash & investments incl. associates at book (FY26) | B35: ='Balance Sheet'!E41 -> 8135.42
A36: − Debt incl. leases (FY26) | B36: ='Balance Sheet'!E12 -> 3928.93
A37: − Non-controlling interests (FY26 book) | B37: ='Balance Sheet'!E9 -> 643.39
A38: Equity value | B38: =B32+B35-B36-B37 -> 108887.06
A39: DCF value per share (₹) | B39: =B38/Historicals!E25 -> 1135.1862
A40: Upside / (downside) vs CMP | B40: =B39/B34-1 -> -0.53741393
A42: SENSITIVITY — DCF value per share (₹): WACC (rows) × terminal growth (columns)
A43: Stage-2 fade path held at base case; only discount rate and terminal growth change. Shaded cells ≥ current price. Base case ≈ WACC 10.9%, g 6.0% (between the 10.5% and 11.0% rows).
A44: WACC ↓ / terminal growth → | B44: 0.05 | C44: 0.055 | D44: 0.06 | E44: 0.065 | F44: 0.07 | G44: 0.08 | H44: 0.09
A45: 0.09 | B45: =IF($A45<=B$44,"n.m.",(SUMPRODUCT($C$23:$Q$23,1/(1+$A45)^$C$24:$Q$24)+$Q$23*(1+B$44)/($A45-B$44)/(1+$A45)^15+$B$35-$B$36-$B$37)/Historicals!$E$25) -> 1523.1043 | C45: =IF($A45<=C$44,"n.m.",(SUMPRODUCT($C$23:$Q$23,1/(1+$A45)^$C$24:$Q$24)+$Q$23*(1+C$44)/($A45-C$44)/(1+$A45)^15+$B$35-$B$36-$B$37)/Historicals!$E$25) -> 1656.4257 | D45: =IF($A45<=D$44,"n.m.",(SUMPRODUCT($C$23:$Q$23,1/(1+$A45)^$C$24:$Q$24)+$Q$23*(1+D$44)/($A45-D$44)/(1+$A45)^15+$B$35-$B$36-$B$37)/Historicals!$E$25) -> 1834.1875 | E45: =IF($A45<=E$44,"n.m.",(SUMPRODUCT($C$23:$Q$23,1/(1+$A45)^$C$24:$Q$24)+$Q$23*(1+E$44)/($A45-E$44)/(1+$A45)^15+$B$35-$B$36-$B$37)/Historicals!$E$25) -> 2083.0541 | F45: =IF($A45<=F$44,"n.m.",(SUMPRODUCT($C$23:$Q$23,1/(1+$A45)^$C$24:$Q$24)+$Q$23*(1+F$44)/($A45-F$44)/(1+$A45)^15+$B$35-$B$36-$B$37)/Historicals!$E$25) -> 2456.3539 | G45: =IF($A45<=G$44,"n.m.",(SUMPRODUCT($C$23:$Q$23,1/(1+$A45)^$C$24:$Q$24)+$Q$23*(1+G$44)/($A45-G$44)/(1+$A45)^15+$B$35-$B$36-$B$37)/Historicals!$E$25) -> 4322.8532 | H45: =IF($A45<=H$44,"n.m.",(SUMPRODUCT($C$23:$Q$23,1/(1+$A45)^$C$24:$Q$24)+$Q$23*(1+H$44)/($A45-H$44)/(1+$A45)^15+$B$35-$B$36-$B$37)/Historicals!$E$25) -> n.m.
A46: 0.095 | B46: =IF($A46<=B$44,"n.m.",(SUMPRODUCT($C$23:$Q$23,1/(1+$A46)^$C$24:$Q$24)+$Q$23*(1+B$44)/($A46-B$44)/(1+$A46)^15+$B$35-$B$36-$B$37)/Historicals!$E$25) -> 1350.6464 | C46: =IF($A46<=C$44,"n.m.",(SUMPRODUCT($C$23:$Q$23,1/(1+$A46)^$C$24:$Q$24)+$Q$23*(1+C$44)/($A46-C$44)/(1+$A46)^15+$B$35-$B$36-$B$37)/Historicals!$E$25) -> 1447.9051 | D46: =IF($A46<=D$44,"n.m.",(SUMPRODUCT($C$23:$Q$23,1/(1+$A46)^$C$24:$Q$24)+$Q$23*(1+D$44)/($A46-D$44)/(1+$A46)^15+$B$35-$B$36-$B$37)/Historicals!$E$25) -> 1572.9521 | E46: =IF($A46<=E$44,"n.m.",(SUMPRODUCT($C$23:$Q$23,1/(1+$A46)^$C$24:$Q$24)+$Q$23*(1+E$44)/($A46-E$44)/(1+$A46)^15+$B$35-$B$36-$B$37)/Historicals!$E$25) -> 1739.6813 | F46: =IF($A46<=F$44,"n.m.",(SUMPRODUCT($C$23:$Q$23,1/(1+$A46)^$C$24:$Q$24)+$Q$23*(1+F$44)/($A46-F$44)/(1+$A46)^15+$B$35-$B$36-$B$37)/Historicals!$E$25) -> 1973.1023 | G46: =IF($A46<=G$44,"n.m.",(SUMPRODUCT($C$23:$Q$23,1/(1+$A46)^$C$24:$Q$24)+$Q$23*(1+G$44)/($A46-G$44)/(1+$A46)^15+$B$35-$B$36-$B$37)/Historicals!$E$25) -> 2906.7862 | H46: =IF($A46<=H$44,"n.m.",(SUMPRODUCT($C$23:$Q$23,1/(1+$A46)^$C$24:$Q$24)+$Q$23*(1+H$44)/($A46-H$44)/(1+$A46)^15+$B$35-$B$36-$B$37)/Historicals!$E$25) -> 7575.2055
A47: 0.1 | B47: =IF($A47<=B$44,"n.m.",(SUMPRODUCT($C$23:$Q$23,1/(1+$A47)^$C$24:$Q$24)+$Q$23*(1+B$44)/($A47-B$44)/(1+$A47)^15+$B$35-$B$36-$B$37)/Historicals!$E$25) -> 1213.0702 | C47: =IF($A47<=C$44,"n.m.",(SUMPRODUCT($C$23:$Q$23,1/(1+$A47)^$C$24:$Q$24)+$Q$23*(1+C$44)/($A47-C$44)/(1+$A47)^15+$B$35-$B$36-$B$37)/Historicals!$E$25) -> 1286.0695 | D47: =IF($A47<=D$44,"n.m.",(SUMPRODUCT($C$23:$Q$23,1/(1+$A47)^$C$24:$Q$24)+$Q$23*(1+D$44)/($A47-D$44)/(1+$A47)^15+$B$35-$B$36-$B$37)/Historicals!$E$25) -> 1377.3186 | E47: =IF($A47<=E$44,"n.m.",(SUMPRODUCT($C$23:$Q$23,1/(1+$A47)^$C$24:$Q$24)+$Q$23*(1+E$44)/($A47-E$44)/(1+$A47)^15+$B$35-$B$36-$B$37)/Historicals!$E$25) -> 1494.6389 | F47: =IF($A47<=F$44,"n.m.",(SUMPRODUCT($C$23:$Q$23,1/(1+$A47)^$C$24:$Q$24)+$Q$23*(1+F$44)/($A47-F$44)/(1+$A47)^15+$B$35-$B$36-$B$37)/Historicals!$E$25) -> 1651.066 | G47: =IF($A47<=G$44,"n.m.",(SUMPRODUCT($C$23:$Q$23,1/(1+$A47)^$C$24:$Q$24)+$Q$23*(1+G$44)/($A47-G$44)/(1+$A47)^15+$B$35-$B$36-$B$37)/Historicals!$E$25) -> 2198.5608 | H47: =IF($A47<=H$44,"n.m.",(SUMPRODUCT($C$23:$Q$23,1/(1+$A47)^$C$24:$Q$24)+$Q$23*(1+H$44)/($A47-H$44)/(1+$A47)^15+$B$35-$B$36-$B$37)/Historicals!$E$25) -> 3841.045
A48: 0.105 | B48: =IF($A48<=B$44,"n.m.",(SUMPRODUCT($C$23:$Q$23,1/(1+$A48)^$C$24:$Q$24)+$Q$23*(1+B$44)/($A48-B$44)/(1+$A48)^15+$B$35-$B$36-$B$37)/Historicals!$E$25) -> 1100.8371 | C48: =IF($A48<=C$44,"n.m.",(SUMPRODUCT($C$23:$Q$23,1/(1+$A48)^$C$24:$Q$24)+$Q$23*(1+C$44)/($A48-C$44)/(1+$A48)^15+$B$35-$B$36-$B$37)/Historicals!$E$25) -> 1156.8895 | D48: =IF($A48<=D$44,"n.m.",(SUMPRODUCT($C$23:$Q$23,1/(1+$A48)^$C$24:$Q$24)+$Q$23*(1+D$44)/($A48-D$44)/(1+$A48)^15+$B$35-$B$36-$B$37)/Historicals!$E$25) -> 1225.398 | E48: =IF($A48<=E$44,"n.m.",(SUMPRODUCT($C$23:$Q$23,1/(1+$A48)^$C$24:$Q$24)+$Q$23*(1+E$44)/($A48-E$44)/(1+$A48)^15+$B$35-$B$36-$B$37)/Historicals!$E$25) -> 1311.0336 | F48: =IF($A48<=F$44,"n.m.",(SUMPRODUCT($C$23:$Q$23,1/(1+$A48)^$C$24:$Q$24)+$Q$23*(1+F$44)/($A48-F$44)/(1+$A48)^15+$B$35-$B$36-$B$37)/Historicals!$E$25) -> 1421.1365 | G48: =IF($A48<=G$44,"n.m.",(SUMPRODUCT($C$23:$Q$23,1/(1+$A48)^$C$24:$Q$24)+$Q$23*(1+G$44)/($A48-G$44)/(1+$A48)^15+$B$35-$B$36-$B$37)/Historicals!$E$25) -> 1773.4659 | H48: =IF($A48<=H$44,"n.m.",(SUMPRODUCT($C$23:$Q$23,1/(1+$A48)^$C$24:$Q$24)+$Q$23*(1+H$44)/($A48-H$44)/(1+$A48)^15+$B$35-$B$36-$B$37)/Historicals!$E$25) -> 2595.5677
A49: 0.11 | B49: =IF($A49<=B$44,"n.m.",(SUMPRODUCT($C$23:$Q$23,1/(1+$A49)^$C$24:$Q$24)+$Q$23*(1+B$44)/($A49-B$44)/(1+$A49)^15+$B$35-$B$36-$B$37)/Historicals!$E$25) -> 1007.5898 | C49: =IF($A49<=C$44,"n.m.",(SUMPRODUCT($C$23:$Q$23,1/(1+$A49)^$C$24:$Q$24)+$Q$23*(1+C$44)/($A49-C$44)/(1+$A49)^15+$B$35-$B$36-$B$37)/Historicals!$E$25) -> 1051.4391 | D49: =IF($A49<=D$44,"n.m.",(SUMPRODUCT($C$23:$Q$23,1/(1+$A49)^$C$24:$Q$24)+$Q$23*(1+D$44)/($A49-D$44)/(1+$A49)^15+$B$35-$B$36-$B$37)/Historicals!$E$25) -> 1104.0583 | E49: =IF($A49<=E$44,"n.m.",(SUMPRODUCT($C$23:$Q$23,1/(1+$A49)^$C$24:$Q$24)+$Q$23*(1+E$44)/($A49-E$44)/(1+$A49)^15+$B$35-$B$36-$B$37)/Historicals!$E$25) -> 1168.3707 | F49: =IF($A49<=F$44,"n.m.",(SUMPRODUCT($C$23:$Q$23,1/(1+$A49)^$C$24:$Q$24)+$Q$23*(1+F$44)/($A49-F$44)/(1+$A49)^15+$B$35-$B$36-$B$37)/Historicals!$E$25) -> 1248.7612 | G49: =IF($A49<=G$44,"n.m.",(SUMPRODUCT($C$23:$Q$23,1/(1+$A49)^$C$24:$Q$24)+$Q$23*(1+G$44)/($A49-G$44)/(1+$A49)^15+$B$35-$B$36-$B$37)/Historicals!$E$25) -> 1489.9326 | H49: =IF($A49<=H$44,"n.m.",(SUMPRODUCT($C$23:$Q$23,1/(1+$A49)^$C$24:$Q$24)+$Q$23*(1+H$44)/($A49-H$44)/(1+$A49)^15+$B$35-$B$36-$B$37)/Historicals!$E$25) -> 1972.2755
A50: 0.115 | B50: =IF($A50<=B$44,"n.m.",(SUMPRODUCT($C$23:$Q$23,1/(1+$A50)^$C$24:$Q$24)+$Q$23*(1+B$44)/($A50-B$44)/(1+$A50)^15+$B$35-$B$36-$B$37)/Historicals!$E$25) -> 928.92883 | C50: =IF($A50<=C$44,"n.m.",(SUMPRODUCT($C$23:$Q$23,1/(1+$A50)^$C$24:$Q$24)+$Q$23*(1+C$44)/($A50-C$44)/(1+$A50)^15+$B$35-$B$36-$B$37)/Historicals!$E$25) -> 963.76947 | D50: =IF($A50<=D$44,"n.m.",(SUMPRODUCT($C$23:$Q$23,1/(1+$A50)^$C$24:$Q$24)+$Q$23*(1+D$44)/($A50-D$44)/(1+$A50)^15+$B$35-$B$36-$B$37)/Historicals!$E$25) -> 1004.9448 | E50: =IF($A50<=E$44,"n.m.",(SUMPRODUCT($C$23:$Q$23,1/(1+$A50)^$C$24:$Q$24)+$Q$23*(1+E$44)/($A50-E$44)/(1+$A50)^15+$B$35-$B$36-$B$37)/Historicals!$E$25) -> 1054.3551 | F50: =IF($A50<=F$44,"n.m.",(SUMPRODUCT($C$23:$Q$23,1/(1+$A50)^$C$24:$Q$24)+$Q$23*(1+F$44)/($A50-F$44)/(1+$A50)^15+$B$35-$B$36-$B$37)/Historicals!$E$25) -> 1114.7455 | G50: =IF($A50<=G$44,"n.m.",(SUMPRODUCT($C$23:$Q$23,1/(1+$A50)^$C$24:$Q$24)+$Q$23*(1+G$44)/($A50-G$44)/(1+$A50)^15+$B$35-$B$36-$B$37)/Historicals!$E$25) -> 1287.2896 | H50: =IF($A50<=H$44,"n.m.",(SUMPRODUCT($C$23:$Q$23,1/(1+$A50)^$C$24:$Q$24)+$Q$23*(1+H$44)/($A50-H$44)/(1+$A50)^15+$B$35-$B$36-$B$37)/Historicals!$E$25) -> 1597.869
A52: REVERSE DCF — what does today's price assume?
A53: Terminal growth that equates DCF value to CMP (at base WACC) | B53: 0.0914
A54: WACC that equates DCF value to CMP (at base terminal growth) | B54: 0.0824
A55: Both solved by bisection in the build script on base inputs (goal seek). If you change inputs, re-run: Data ▸ What-If ▸ Goal Seek (set B39 = B34 by changing Assumptions!B31, or the WACC inputs).

Sheet Scenarios
A1: Bear / Base / Bull Scenarios — FY27E–FY28E
A2: Base links to Assumptions. Bear and bull ranges are anchored to FY24–FY26 actuals and FY27 guidance (see column H)
B3: BEAR | D3: BASE | F3: BULL
A4: Driver | B4: Bear FY27E | C4: Bear FY28E | D4: Base FY27E | E4: Base FY28E | F4: Bull FY27E | G4: Bull FY28E | H4: Evidence for the range
A5: INPUTS (blue = scenario input · green = base case linked from Assumptions)
A6: Decorative volume growth | B6: 0.06 | C6: 0.05 | D6: =Assumptions!B6 -> 0.09 | E6: =Assumptions!C6 -> 0.08 | F6: 0.1 | G6: 0.1 | H6: Bear: below the 8% guidance floor, between FY25 (2.5%) and FY26 (9%). Bull: top of 8–10% guidance; FY26 Q2/Q4 printed 10.9%/12.4%.
A7: Price / mix | B7: 0.03 | C7: -0.01 | D7: =Assumptions!B7 -> 0.05 | E7: =Assumptions!C7 -> 0.01 | F7: 0.06 | G7: 0.02 | H7: Bear: price hikes partly reversed as Opus fills capacity; FY28 back to negative (FY24–26 were −4% to −8%). Bull: most of Q1FY27's +7% holds.
A8: International growth | B8: 0.08 | C8: 0.06 | D8: =Assumptions!B8 -> 0.12 | E8: =Assumptions!C8 -> 0.09 | F8: 0.15 | G8: 0.1 | H8: FY26 +9.4%; Q1FY27 +27%. Bear includes currency pressure in Egypt / Ethiopia / Sri Lanka.
A9: Industrial growth | B9: 0.1 | C9: 0.08 | D9: =Assumptions!B9 -> 0.14 | E9: =Assumptions!C9 -> 0.1 | F9: 0.16 | G9: 0.12 | H9: FY26 +12.4%; Q1FY27 'mid-teens'.
A10: Gross margin | B10: 0.415 | C10: 0.42 | D10: =Assumptions!B12 -> 0.428 | E10: =Assumptions!C12 -> 0.435 | F10: 0.435 | G10: 0.444 | H10: Bear ≈ FY25 trough (42.4%) less crude shock. Bull ≈ FY26 standalone level (44.4%) as VAE savings arrive.
A11: Employee cost % revenue | B11: 0.076 | C11: 0.076 | D11: =Assumptions!B13 -> 0.075 | E11: =Assumptions!C13 -> 0.074 | F11: 0.074 | G11: 0.072 | H11: Bear: FY26 level (7.9%) less a little leverage. Bull: FY24-like leverage.
A12: Other expenses % revenue | B12: 0.168 | C12: 0.168 | D12: =Assumptions!B14 -> 0.166 | E12: =Assumptions!C14 -> 0.166 | F12: 0.164 | G12: 0.163 | H12: Bear: ad-spend stays at FY26 intensity (17.1%). Bull: moderates toward FY24 (15.5%).
A13: Target P/E on FY28E EPS | C13: 40 | E13: =Assumptions!B32 -> 45 | G13: 52 | H13: Bear 40x: below Berger (43x) — no leadership premium. Bull 52x: ≈ AP 3-yr median trailing (50x) and ICICI Direct's 52x FY28E (Jun-2026).
A14: OUTPUTS (calculated — do not overwrite)
A15: Decorative & home décor revenue | B15: =Historicals!$E$40*(1+B6)*(1+B7) -> 33660.631 | C15: =B15*(1+C6)*(1+C7) -> 34990.226 | D15: =Historicals!$E$40*(1+D6)*(1+D7) -> 35285.393 | E15: =D15*(1+E6)*(1+E7) -> 38489.306 | F15: =Historicals!$E$40*(1+F6)*(1+F7) -> 35948.246 | G15: =F15*(1+G6)*(1+G7) -> 40333.932
A16: International revenue | B16: =Historicals!$E$41*(1+B8) -> 3621.888 | C16: =B16*(1+C8) -> 3839.2013 | D16: =Historicals!$E$41*(1+D8) -> 3756.032 | E16: =D16*(1+E8) -> 4094.0749 | F16: =Historicals!$E$41*(1+F8) -> 3856.64 | G16: =F16*(1+G8) -> 4242.304
A17: Industrial revenue | B17: =Historicals!$E$42*(1+B9) -> 1465.64 | C17: =B17*(1+C9) -> 1582.8912 | D17: =Historicals!$E$42*(1+D9) -> 1518.936 | E17: =D17*(1+E9) -> 1670.8296 | F17: =Historicals!$E$42*(1+F9) -> 1545.584 | G17: =F17*(1+G9) -> 1731.0541
A18: Other operating revenue | B18: =Assumptions!$B$10 -> 67.2 | C18: =Assumptions!$C$10 -> 67.2 | D18: =Assumptions!$B$10 -> 67.2 | E18: =Assumptions!$C$10 -> 67.2 | F18: =Assumptions!$B$10 -> 67.2 | G18: =Assumptions!$C$10 -> 67.2
A19: Revenue from operations | B19: =SUM(B15:B18) -> 38815.359 | C19: =SUM(C15:C18) -> 40479.518 | D19: =SUM(D15:D18) -> 40627.561 | E19: =SUM(E15:E18) -> 44321.411 | F19: =SUM(F15:F18) -> 41417.67 | G19: =SUM(G15:G18) -> 46374.491
A20: EBITDA (excl. OI) | B20: =B19*(B10-B11-B12) -> 6637.4263 | C20: =C19*(C10-C11-C12) -> 7124.3952 | D20: =D19*(D10-D11-D12) -> 7597.3539 | E20: =E19*(E10-E11-E12) -> 8642.6751 | F20: =F19*(F10-F11-F12) -> 8159.2811 | G20: =G19*(G10-G11-G12) -> 9692.2685
A21: EBITDA margin | B21: =B20/B19 -> 0.171 | C21: =C20/C19 -> 0.176 | D21: =D20/D19 -> 0.187 | E21: =E20/E19 -> 0.195 | F21: =F20/F19 -> 0.197 | G21: =G20/G19 -> 0.209
A22: D&A | B22: =B19*Assumptions!$B$15 -> 1319.7222 | C22: =C19*Assumptions!$C$15 -> 1376.3036 | D22: =D19*Assumptions!$B$15 -> 1381.3371 | E22: =E19*Assumptions!$C$15 -> 1506.928 | F22: =F19*Assumptions!$B$15 -> 1408.2008 | G22: =G19*Assumptions!$C$15 -> 1576.7327
A23: Other income | B23: =B19*Assumptions!$B$16 -> 698.67646 | C23: =C19*Assumptions!$C$16 -> 728.63133 | D23: =D19*Assumptions!$B$16 -> 731.29609 | E23: =E19*Assumptions!$C$16 -> 797.7854 | F23: =F19*Assumptions!$B$16 -> 745.51807 | G23: =G19*Assumptions!$C$16 -> 834.74083
A24: Finance costs | B24: =Assumptions!$B$17 -> 200 | C24: =Assumptions!$C$17 -> 200 | D24: =Assumptions!$B$17 -> 200 | E24: =Assumptions!$C$17 -> 200 | F24: =Assumptions!$B$17 -> 200 | G24: =Assumptions!$C$17 -> 200
A25: PBT | B25: =B20-B22+B23-B24 -> 5816.3806 | C25: =C20-C22+C23-C24 -> 6276.7229 | D25: =D20-D22+D23-D24 -> 6747.3129 | E25: =E20-E22+E23-E24 -> 7733.5326 | F25: =F20-F22+F23-F24 -> 7296.5983 | G25: =G20-G22+G23-G24 -> 8750.2767
A26: Net profit to owners | B26: =B25*(1-Assumptions!$B$18)+Assumptions!$B$19 -> 4404.1216 | C26: =C25*(1-Assumptions!$C$18)+Assumptions!$C$19 -> 4744.7749 | D26: =D25*(1-Assumptions!$B$18)+Assumptions!$B$19 -> 5093.0115 | E26: =E25*(1-Assumptions!$C$18)+Assumptions!$C$19 -> 5822.8141 | F26: =F25*(1-Assumptions!$B$18)+Assumptions!$B$19 -> 5499.4828 | G26: =G25*(1-Assumptions!$C$18)+Assumptions!$C$19 -> 6575.2047
A27: EPS (₹) | B27: =B26/Historicals!$E$25 -> 45.914529 | C27: =C26/Historicals!$E$25 -> 49.465961 | D27: =D26/Historicals!$E$25 -> 53.096451 | E27: =E26/Historicals!$E$25 -> 60.704901 | F27: =F26/Historicals!$E$25 -> 57.334057 | G27: =G26/Historicals!$E$25 -> 68.54884
A29: SUMMARY
A30: FY28E | B30: Bear | C30: Base | D30: Bull
A31: Revenue (₹ cr) | B31: =C19 -> 40479.518 | C31: =E19 -> 44321.411 | D31: =G19 -> 46374.491
A32: EBITDA (₹ cr) | B32: =C20 -> 7124.3952 | C32: =E20 -> 8642.6751 | D32: =G20 -> 9692.2685
A33: EBITDA margin | B33: =C21 -> 0.176 | C33: =E21 -> 0.195 | D33: =G21 -> 0.209
A34: EPS (₹) | B34: =C27 -> 49.465961 | C34: =E27 -> 60.704901 | D34: =G27 -> 68.54884
A35: Target P/E | B35: =C13 -> 40 | C35: =E13 -> 45 | D35: =G13 -> 52
A36: Target price (₹) | B36: =ROUND(B34*B35,-1) -> 1980 | C36: =ROUND(C34*C35,-1) -> 2730 | D36: =ROUND(D34*D35,-1) -> 3560
A37: Upside / (downside) vs CMP | B37: =B36/Assumptions!$B$33-1 -> -0.19315403 | C37: =C36/Assumptions!$B$33-1 -> 0.11246944 | D37: =D36/Assumptions!$B$33-1 -> 0.45069275
A38: Illustrative probability weight | B38: 0.25 | C38: 0.5 | D38: 0.25
A39: Probability-weighted target (₹) | B39: =ROUND(SUMPRODUCT(B36:D36,B38:D38),-1) -> 2750
A40: Probability-weighted upside | B40: =B39/Assumptions!$B$33-1 -> 0.1206194
A42: BEAR — 'FY25 again': Birla Opus fills its capacity with price-led offers, volume slips below guidance, price hikes are partly given back and crude stays above $100. Margins return to FY25 levels and the market removes the leadership premium.
A43: BASE — 'recovery within guidance': volume 8–9%, price/mix positive in FY27 then +1%, gross margin dips in FY27 and recovers, EBITDA margin stays inside 18–20%.
A44: BULL — 'FY24-type margins': volume at the top of guidance, most of the price increase sticks, VAE backward integration lifts gross margin to ~44.4% and ad-spend intensity eases.

Sheet Quarterly Tracker
A1: Quarterly Earnings Tracker — Q1 FY26 to Q1 FY27 (consolidated unless stated)
A2: Coverage log: what was reported, what management guided, what the Street expected, and what it means for the model
A4: Metric | B4: Q1 FY26 | C4: Q2 FY26 | D4: Q3 FY26 | E4: Q4 FY26 | F4: Q1 FY27 | G4: Source / basis
A5: Result date | B5: 29-Jul-2025 | C5: 12-Nov-2025 | D5: 27-Jan-2026 | E5: 29-May-2026 | F5: 29-Jul-2026
A6: Revenue from operations (₹ cr) | B6: 8939 | C6: 8531.3 | D6: 8867 | E6: 9246.7 | F6: 10541.9 | G6: Results releases (via Screener/MarketsMojo/Upstox). Q1FY26 rounded.
A7: Revenue growth YoY | B7: -0.003 | C7: 0.063 | D7: 0.037 | E7: 0.106 | F7: 0.179 | G7: As reported in coverage of each release
A8: Decorative India volume growth | B8: 0.039 | C8: 0.109 | D8: 0.079 | E8: 0.124 | F8: 0.09 | G8: Company releases / call summaries
A9: Decorative India value growth | B9: -0.012 | C9: 0.06 | D9: 0.028 | E9: 0.102 | F9: 0.166 | G9: Q1FY26: −1.2% is standalone revenue (proxy) — verify decorative value in Q1FY26 release
A10: Implied price/mix | B10: =(1+B9)/(1+B8)-1 -> -0.049085659 | C10: =(1+C9)/(1+C8)-1 -> -0.04418395 | D10: =(1+D9)/(1+D8)-1 -> -0.047265987 | E10: =(1+E9)/(1+E8)-1 -> -0.019572954 | F10: =(1+F9)/(1+F8)-1 -> 0.069724771 | G10: Derived
A11: Gross margin | B11: 0.427 | C11: 0.437 | D11: 0.443 | E11: 0.448 | F11: 0.438 | G11: Consolidated except Q2FY26 and Q1FY27 = standalone (consolidated not sourced). Q1 & Q4: ICICI Direct; Q2: FilingReader; Q3: Quartr; Q1FY27: call
A12: Gross margin basis | B12: Consol. | C12: Standalone | D12: Consol. | E12: Consol. | F12: Standalone
A13: EBITDA margin (excl. OI) | B13: 0.182 | C13: 0.176 | D13: 0.201 | E13: 0.193 | F13: 0.206 | G13: Operating profit / revenue from ops
A14: Net profit to owners (₹ cr) | B14: 1100 | C14: 993.6 | D14: 1059.9 | E14: 1172.1 | F14: 1539.3 | G14: Q3 after ₹158 cr exceptional (White Teak impairment, Labour Code). Q1FY26 rounded.
A15: Management guidance given | B15: EBITDA 18–20% maintained | C15: FY26: high-single-digit volume, mid-single-digit value; EBITDA 18–20% | D15: EBITDA 18–20% maintained | E15: EBITDA 18–20%; cumulative price hikes ~10.5–11% | F15: FY27: volume 8–10%, value > volume; EBITDA 18–20% | G15: Call summaries (Quartr, Sharekhan, FilingReader, Business Standard) — verify vs transcripts on BSE
A16: Street expectation vs actual | B16: EPS ₹11.47 vs ~₹10.98 consensus (beat) | C16: EPS ₹10.36 vs ~₹8.96 consensus (beat) | D16: Volume 7.9% seen as disappointing (HSBC downgrade) | E16: PAT ₹1,172 cr vs ₹900–1,000 cr expected (beat) | F16: Volume 9% vs ~12% pre-result estimate (miss); margin beat | G16: TipRanks, TradingView, Substack/HSBC note, Univest, Zee Business previews — secondary sources, reference only
A17: Read-across to the model | B17: — | C17: — | D17: — | E17: Base-year for forecast | F17: ="Q1 = "&TEXT(F6/Forecast!D15,"0.0%")&" of FY27E vs "&TEXT(B6/Historicals!E6,"0.0%")&" last year" -> Q1 = 25.9% of FY27E vs 25.1% last year | G17: If Q1 share of the year is above last year's, FY27E revenue may be conservative
A18: Sum of FY26 quarterly revenue (check) | E18: =SUM(B6:E6) -> 35584 | G18: Should equal FY26 annual revenue 35,583.5 (see Checks)

Sheet Driver Tree
A1: Business Driver Tree — how filings map into the forecast
A2: Type: FACT = from filings/results · GUIDANCE = management statement · ASSUMPTION = analyst judgement · NOT DISCLOSED = no public data
A4: Driver | B4: FY24A | C4: FY25A | D4: FY26A | E4: Q1 FY27A | F4: FY27E | G4: FY28E | H4: Type | I4: Evidence / source
A5: REVENUE = Σ segments; Decorative & home décor = Volume × Realisation
A6: Revenue from operations (₹ cr) | B6: =Historicals!C6 -> 35494.73 | C6: =Historicals!D6 -> 33905.62 | D6: =Historicals!E6 -> 35583.54 | E6: ='Quarterly Tracker'!F6 -> 10541.9 | F6: =Forecast!D15 -> 40627.561 | G6: =Forecast!E15 -> 44321.411
A7: ├ Decorative & home décor revenue (₹ cr) | C7: =Historicals!D40 -> 29545.3 | D7: =Historicals!E40 -> 30830.4 | F7: =Forecast!D9 -> 35285.393 | G7: =Forecast!E9 -> 38489.306
A8: │ ├ VOLUME growth (Decorative India) | B8: =Historicals!C49 -> 0.1 | C8: =Historicals!D49 -> 0.025 | D8: =Historicals!E49 -> 0.09 | E8: ='Quarterly Tracker'!F8 -> 0.09 | F8: =Forecast!D6 -> 0.09 | G8: =Forecast!E6 -> 0.08
A9: │ │ · Industry demand | C9: Decline | H9: FACT (qual.) | I9: IAR FY25 MD&CEO letter: industry revenue ranged from low-single-digit decline to flat in FY25. Industry volume: NOT DISCLOSED.
A10: │ │ · Market share | H10: NOT DISCLOSED | I10: Asian Paints does not publish share. Birla Opus: ~10% revenue share by Mar-26, +370bp in FY26 (Grasim).
A11: │ │ · Rural vs urban | E11: Rural > urban | H11: FACT (qual.) | I11: Q1FY27 call: rural (T3/T4) outpaced urban; B2B strong. Not quantified.
A12: │ │ · Competitive capacity | D12: ~24% | H12: FACT (competitor) | I12: Birla Opus ~24% of industry decorative capacity (Grasim Q2/Q3 FY26 releases).
A13: │ └ REALISATION (price/mix) | B13: =Historicals!C51 -> -0.055454545 | C13: =Historicals!D51 -> -0.08 | D13: =Historicals!E51 -> -0.043119266 | E13: ='Quarterly Tracker'!F10 -> 0.069724771 | F13: =Forecast!D7 -> 0.05 | G13: =Forecast!E7 -> 0.01
A14: │ · Price increases taken | D14: 10.5–11% | E14: ~7% | H14: GUIDANCE/FACT | I14: Cumulative decorative price increase ~10.5–11% (Q4FY26); ~7% effective in Q1FY27 (call summaries).
A15: │ · Mix (premium vs economy) | B15: Down-trade | C15: Down-trade | D15: Improving | H15: FACT (qual.) | I15: FY24–25 releases cite down-trading and price cuts; FY26 cites premium/luxury growth.
A16: ├ International revenue growth | D16: =Forecast!C10 -> 0.093660318 | E16: 0.272 | F16: =Forecast!D10 -> 0.12 | G16: =Forecast!E10 -> 0.09 | H16: FACT → ASSUMPTION | I16: FY26 +9.4% (AR segment); Q1FY27 +27.2% in INR (release).
A17: └ Industrial revenue growth | D17: =Forecast!C12 -> 0.12372438 | F17: =Forecast!D12 -> 0.14 | G17: =Forecast!E12 -> 0.1 | H17: FACT → ASSUMPTION | I17: AP-PPG only (PPGAP is an associate). Q1FY27 'mid-teens'.
A19: GROSS MARGIN = f(raw-material cost, price/mix, sourcing & backward integration)
A20: Gross margin (revenue basis) | B20: =Historicals!C31 -> 0.43399457 | C20: =Historicals!D31 -> 0.4244087 | D20: =Historicals!E31 -> 0.43789235 | E20: ='Quarterly Tracker'!F11 -> 0.438 | F20: =Forecast!D19 -> 0.428 | G20: =Forecast!E19 -> 0.435 | H20: FACT → ASSUMPTION | I20: Q1FY27 figure is standalone.
A21: · Raw-material prices (crude-linked) | B21: Deflation | C21: Mixed | D21: Deflation | E21: Inflation | H21: FACT (qual.) | I21: Releases cite deflation in FY24/FY26; Q1FY27 call cites sharp inflation. Brent ~$105 (Sep-26). Company RM index: NOT DISCLOSED.
A22: · Backward integration (VAE/VAM, white cement) | F22: Starts | H22: FACT + GUIDANCE | I22: Dahej VAE plant commercial production 17-Sep-2026 (BSE filing). Margin benefit is a management claim — size not verified.
A24: EBITDA = gross profit − employee cost − other expenses
A25: Employee cost % revenue | B25: =Historicals!C35 -> 0.065535926 | C25: =Historicals!D35 -> 0.076601755 | D25: =Historicals!E35 -> 0.078676545 | F25: =Forecast!D21 -> 0.075 | G25: =Forecast!E21 -> 0.074 | H25: FACT → ASSUMPTION
A26: Other expenses % revenue (ads, freight, distribution) | B26: =Historicals!C36 -> 0.15476551 | C26: =Historicals!D36 -> 0.17066197 | D26: =Historicals!E36 -> 0.17104116 | F26: =Forecast!D23 -> 0.166 | G26: =Forecast!E23 -> 0.166 | H26: FACT → ASSUMPTION | I26: Advertising split in Note 27 not yet extracted.
A27: EBITDA margin (excl. OI) | B27: =Historicals!C32 -> 0.21369313 | C27: =Historicals!D32 -> 0.17714497 | D27: =Historicals!E32 -> 0.18817464 | E27: ='Quarterly Tracker'!F13 -> 0.206 | F27: =Forecast!D26 -> 0.187 | G27: =Forecast!E26 -> 0.195 | H27: FACT → ASSUMPTION | I27: GUIDANCE: 18–20% for FY27 (Q1FY27 call).

Sheet Competition
A1: Competitive Landscape — decorative paints
A2: Blank-looking cells say 'Not disclosed' or 'Not sourced' on purpose: no figure has been estimated
A4: Metric | B4: Asian Paints | C4: Berger Paints | D4: Kansai Nerolac | E4: Birla Opus (Grasim) | F4: Source / notes
A5: FY26 revenue (₹ cr, consolidated) | B5: =Historicals!E6 -> 35583.54 | C5: 11880 | D5: 8052 | E5: Not separately disclosed | F5: AP: IAR FY26. Peers: Screener. Grasim reports paints within standalone results.
A6: FY26 revenue growth | B6: =Historicals!E30 -> 0.049487961 | C6: =Valuation!E20 -> 0.02901689 | D6: =Valuation!E21 -> 0.029272658 | E6: ~100% (revenue doubled) | F6: Birla Opus: Grasim Q4FY26 commentary (Business Today, Aug-2026).
A7: Q1 FY27 revenue growth | B7: ='Quarterly Tracker'!F7 -> 0.179 | C7: =Valuation!F20 -> 0.11965011 | D7: =Valuation!F21 -> 0.098057354 | E7: Not disclosed | F7: Quarterly revenue from Screener; Opus Q4FY26 +52% like-for-like (Grasim call).
A8: FY26 EBITDA margin (excl. OI) | B8: =Historicals!E32 -> 0.18817464 | C8: =1833/11880 -> 0.15429293 | D8: =975/8052 -> 0.12108793 | E8: Not separately disclosed | F8: Peers: Screener FY26 operating profit / sales.
A9: Decorative share of revenue | B9: 86.8% (deco + home décor) | C9: Not sourced | D9: Not sourced (industrial leader) | E9: ~100% decorative | F9: AP: IAR FY26 Financial Review. Kansai described as industrial-coatings leader (Screener profile).
A10: Decorative capacity | B10: 2,290,000 KL/yr (India) | C10: Not sourced | D10: Not sourced | E10: 1,332 MLPA (~24% of industry) | F10: AP: IAR FY26. Opus: Grasim Q2FY26 release.
A11: Revenue market share | B11: Not disclosed | C11: Not disclosed | D11: Not disclosed | E11: ~10% (Mar-2026) | F11: Grasim Q4FY26 (company estimate).
A12: Share change FY26 | B12: Not disclosed | C12: Not disclosed | D12: Not disclosed | E12: +370 bp | F12: Grasim Q4FY26 call (via Arthneeti summary) — verify in transcript.
A13: Distribution reach | B13: 169,000+ retail touchpoints (FY25) | C13: 1,900+ stores, 2,100+ tinting machines | D13: Not sourced | E13: 11,500+ towns, 50,000+ dealers | F13: AP: IAR FY25. Berger: Q1FY27 call summary. Opus: Grasim Q4FY26.
A14: Latest decorative volume growth | B14: =Historicals!E49 -> 0.09 | C14: High single digit (Q1FY27, standalone) | D14: Not sourced | E14: Not disclosed | F14: AP FY26; Berger Q1FY27 call summary (Tickertape).
A15: ROCE (Screener basis) | B15: 0.263 | C15: 0.216 | D15: 0.12 | E15: n/a (not listed) | F15: Screener, Sep-2026.
A16: Trailing P/E | B16: =Valuation!N19 -> 49.402932 | C16: =Valuation!N20 -> 42.8 | D16: =Valuation!N21 -> 23.1 | E16: n/a (not listed) | F16: See Valuation sheet.
A18: Reading: Asian Paints still grew faster than listed peers in FY26 and Q1 FY27, but the only player gaining share at pace is Birla Opus — and its margins are not disclosed, so how long Grasim can fund price-led growth is the key unknown.

Sheet Thesis Breakers
A1: Thesis Breakers — what would prove this view wrong
A2: Thresholds are taken from guidance or past actuals, not picked for effect. Update 'Latest reading' each quarter
A4: Signal | B4: Threshold | C4: Why this threshold | D4: Latest reading | E4: Status
A5: RECOVERY THESIS WEAKENS IF…
A6: Decorative volume growth | B6: < 8% for 2 quarters in a row | C6: Bottom of FY27 guidance (8–10%) | D6: ='Quarterly Tracker'!F8 -> 0.09 | E6: =IF(D6<0.08,"WATCH","OK") -> OK
A7: Price/mix | B7: Turns negative again | C7: FY24–FY26 were −5.5%, −8.0%, −4.3%; Q1FY27 +7.0% is the turn the thesis relies on | D7: ='Quarterly Tracker'!F10 -> 0.069724771 | E7: =IF(D7<0,"BREACH","OK") -> OK
A8: Gross margin | B8: < 42.4% for 2 quarters despite price hikes | C8: FY25 trough (42.4%); would mean price increases are not covering inputs | D8: ='Quarterly Tracker'!F11 -> 0.438 | E8: =IF(D8<0.424,"WATCH","OK") -> OK
A9: EBITDA margin (excl. OI) | B9: < 18% over a half-year | C9: Floor of management's 18–20% range | D9: ='Quarterly Tracker'!F13 -> 0.206 | E9: =IF(D9<0.18,"WATCH","OK") -> OK
A10: Birla Opus share gains | B10: > +370bp/yr while AP volume < 8% | C10: FY26 pace reported by Grasim; faster gains with weak AP volume = share loss | D10: ~10% share | E10: ="Monitor (Grasim quarterly)" -> Monitor (Grasim quarterly)
A11: Volume response to price hikes | B11: Volume < 8% while value > 12% | C11: Would mean price is being bought with volume (Q1FY27: 9% vol / 16.6% value) | D11: ='Quarterly Tracker'!F8 -> 0.09 | E11: =IF(AND(D11<0.08,'Quarterly Tracker'!F9>0.12),"WATCH","OK") -> OK
A13: VALUATION VIEW BECOMES MORE POSITIVE IF…
A14: FY28E EPS path | B14: ≥ bull-case EPS | C14: Bull case requires top-of-guidance volume and ~44.4% gross margin | D14: =Scenarios!D34 -> 68.54884 | E14: ="Base "&TEXT(Forecast!E37,"0.0")&" vs bull "&TEXT(D14,"0.0") -> Base 60.7 vs bull 68.5
A15: Gross margin sustained | B15: ≥ 44.4% with volume ≥ 10% | C15: FY26 standalone level; would support bull-case margins | D15: =Historicals!E31 -> 0.43789235 | E15: =IF(D15>=0.444,"MET","Not yet") -> Not yet
A16: Share price | B16: ="≤ ₹"&TEXT(Valuation!B46,"#,##0")&" (>15% upside)" -> ≤ ₹2,374 (>15% upside) | C16: Price at which the base target implies >15% upside | D16: =Assumptions!B33 -> 2454 | E16: =IF(D16<=Valuation!B46,"MET","No: threshold = "&TEXT(Valuation!B47,"0.0")&"x FY28E") -> No: threshold = 39.1x FY28E
A17: Competitive intensity | B17: Opus share gains slow below +150bp/yr | C17: Less than half the FY26 pace — pricing pressure would ease | D17: Not yet | E17: ="Monitor" -> Monitor
A19: VALUATION VIEW BECOMES MORE NEGATIVE IF…
A20: Share price | B20: ="≥ ₹"&TEXT(Valuation!B48,"#,##0")&" (>10% downside)" -> ≥ ₹3,033 (>10% downside) | C20: Multiple would exceed the threshold P/E with no EPS upgrade | D20: =Assumptions!B33 -> 2454 | E20: =IF(D20>=Valuation!B48,"MET","No: threshold = "&TEXT(Valuation!B49,"0.0")&"x FY28E") -> No: threshold = 50.0x FY28E
A21: FY28E EPS path | B21: ≤ bear-case EPS | C21: Bear case = FY25-type margins with sub-guidance volume | D21: =Scenarios!B34 -> 49.465961 | E21: ="Monitor" -> Monitor

Sheet Checks
A1: Checks — reconciliation to filings and model integrity
A2: Status must read OK. 'EXPLAINED' = known definitional difference, documented in column G
A4: Check | B4: Model | C4: Reference | D4: Difference | E4: Tolerance | F4: Status | G4: What it tests / explanation
A5: A. RECONCILIATION TO FILINGS
A6: FY26 revenue from operations | B6: =Historicals!E6 -> 35583.54 | C6: 35583.5 | D6: =B6-C6 -> 0.04 | E6: 0.1 | F6: =IF(ABS(D6)<=E6,"OK","CHECK") -> OK | G6: Ten-Year Review p.78–79
A7: FY26 PBT incl. associates | B7: =Historicals!E19+Historicals!E22 -> 6003.44 | C7: 6003.44 | D7: =B7-C7 -> 0 | E7: 0.05 | F7: =IF(ABS(D7)<=E7,"OK","CHECK") -> OK | G7: IAR FY26 P&L: PBT 6,003.44 (model PBT excludes associates)
A8: FY25 PBT incl. associates | B8: =Historicals!D19+Historicals!D22 -> 5103.07 | C8: 5103.07 | D8: =B8-C8 -> 0 | E8: 0.05 | F8: =IF(ABS(D8)<=E8,"OK","CHECK") -> OK | G8: IAR FY26 P&L comparative
A9: FY24 PBT incl. associates | B9: =Historicals!C19+Historicals!C22 -> 7347.77 | C9: 7347.77 | D9: =B9-C9 -> 0 | E9: 0.05 | F9: =IF(ABS(D9)<=E9,"OK","CHECK") -> OK | G9: IAR FY25 P&L comparative
A10: FY23 PBT before exceptionals incl. associates | B10: =Historicals!B19-Historicals!B18+Historicals!B22 -> 5737.7 | C10: 5737.7 | D10: =B10-C10 -> 0 | E10: 0.1 | F10: =IF(ABS(D10)<=E10,"OK","CHECK") -> OK | G10: Ten-Year Review (verifies FY23 aggregator P&L)
A11: FY26 company EBITDA (incl. other income) | B11: =Historicals!E14+Historicals!E15 -> 7419.72 | C11: 7419.72 | D11: =B11-C11 -> 0 | E11: 0.05 | F11: =IF(ABS(D11)<=E11,"OK","CHECK") -> OK | G11: IAR FY26 P&L EBITDA line
A12: FY26 net profit to owners | B12: =Historicals!E24 -> 4325.35 | C12: 4325.35 | D12: =B12-C12 -> 0 | E12: 0.05 | F12: =IF(ABS(D12)<=E12,"OK","CHECK") -> OK | G12: IAR FY26 P&L
A13: FY23 net profit to owners | B13: =Historicals!B24 -> 4106.45 | C13: 4106.5 | D13: =B13-C13 -> -0.05 | E13: 0.1 | F13: =IF(ABS(D13)<=E13,"OK","CHECK") -> OK | G13: Ten-Year Review
A14: FY26 EPS: model vs company basic | B14: =Historicals!E26 -> 45.093307 | C14: =Historicals!E27 -> 45.12 | D14: =B14-C14 -> -0.026693078 | E14: 0.05 | F14: =IF(ABS(D14)<=E14,"OK","EXPLAINED") -> OK | G14: EXPLAINED: company divides by weighted shares net of ESOP-trust treasury shares (~95.86 cr)
A15: FY26 gross margin on net sales vs company 43.7% | B15: =(Historicals!E43-Historicals!E10)/Historicals!E43 -> 0.43682975 | C15: =Historicals!E52 -> 0.437 | D15: =B15-C15 -> -0.00017025374 | E15: 0.001 | F15: =IF(ABS(D15)<=E15,"OK","CHECK") -> OK | G15: Company GM uses net sales, not revenue from operations
A16: FY26 segments sum to consolidated net sales | B16: =Historicals!E44 -> 35516.4 | C16: =Historicals!E43 -> 35516.4 | D16: =B16-C16 -> 0 | E16: 0.1 | F16: =IF(ABS(D16)<=E16,"OK","CHECK") -> OK | G16: Financial Review segment table vs Ten-Year Review
A17: FY25 segments sum to consolidated net sales | B17: =Historicals!D44 -> 33797.4 | C17: =Historicals!D43 -> 33797.4 | D17: =B17-C17 -> 0 | E17: 0.1 | F17: =IF(ABS(D17)<=E17,"OK","CHECK") -> OK | G17: As above
A18: FY26 net sales + other op. revenue = revenue | B18: =Historicals!E43+Historicals!E45 -> 35583.6 | C18: =Historicals!E6 -> 35583.54 | D18: =B18-C18 -> 0.06 | E18: 0.2 | F18: =IF(ABS(D18)<=E18,"OK","CHECK") -> OK | G18: Ten-Year Review
A19: FY26 book value per share vs company ₹222.8 | B19: ='Balance Sheet'!E44 -> 222.8064 | C19: 222.8 | D19: =B19-C19 -> 0.0064011676 | E19: 0.1 | F19: =IF(ABS(D19)<=E19,"OK","CHECK") -> OK | G19: Ten-Year Review
A20: FY26 borrowings: Ten-Year Review vs balance sheet | B20: ='Balance Sheet'!E10+31.67 -> 2324.93 | C20: 2324.9 | D20: =B20-C20 -> 0.03 | E20: 0.1 | F20: =IF(ABS(D20)<=E20,"OK","EXPLAINED") -> OK | G20: EXPLAINED: Ten-Year Review 'borrowings' also includes ₹31.67 cr 'other liabilities' (govt. loans) — CF note p.467
A21: FY26 net change in cash vs cash flow statement | B21: ='Cash Flow'!E10 -> 3377.6 | C21: ='Cash Flow'!E21 -> 3377.6 | D21: =B21-C21 -> 0 | E21: 0.05 | F21: =IF(ABS(D21)<=E21,"OK","CHECK") -> OK | G21: IAR FY26 cash flow
A22: FY25 net change in cash | B22: ='Cash Flow'!D10 -> -202.74 | C22: ='Cash Flow'!D21 -> -202.74 | D22: =B22-C22 -> 0 | E22: 0.05 | F22: =IF(ABS(D22)<=E22,"OK","CHECK") -> OK | G22: IAR FY26 cash flow comparative
A23: FY24 net change in cash | B23: ='Cash Flow'!C10 -> 603.47 | C23: ='Cash Flow'!C21 -> 603.47 | D23: =B23-C23 -> 0 | E23: 0.05 | F23: =IF(ABS(D23)<=E23,"OK","CHECK") -> OK | G23: IAR FY25 cash flow comparative
A24: Sum of FY26 quarters = FY26 revenue | B24: ='Quarterly Tracker'!E18 -> 35584 | C24: =Historicals!E6 -> 35583.54 | D24: =B24-C24 -> 0.46 | E24: 2 | F24: =IF(ABS(D24)<=E24,"OK","CHECK") -> OK | G24: Quarterly releases vs annual report (Q1 figure rounded)
A25: B. MODEL INTEGRITY
A26: Forecast FY26A segment build = reported revenue | B26: =Forecast!C15 -> 35583.6 | C26: =Historicals!E6 -> 35583.54 | D26: =B26-C26 -> 0.06 | E26: 0.2 | F26: =IF(ABS(D26)<=E26,"OK","CHECK") -> OK | G26: Driver build starts from filed segment data
A27: Forecast FY25A segment build = reported revenue | B27: =Forecast!B15 -> 33905.7 | C27: =Historicals!D6 -> 33905.62 | D27: =B27-C27 -> 0.08 | E27: 0.2 | F27: =IF(ABS(D27)<=E27,"OK","CHECK") -> OK | G27: As above
A28: Scenario base FY28E EPS = Forecast FY28E EPS | B28: =Scenarios!E27 -> 60.704901 | C28: =Forecast!E37 -> 60.704901 | D28: =B28-C28 -> 0 | E28: 0.001 | F28: =IF(ABS(D28)<=E28,"OK","CHECK") -> OK | G28: Scenario engine replicates the forecast
A29: DCF stage-1 FCFF = Forecast FCFF | B29: =SUM(DCF!C23:G23) -> 23727.491 | C29: =SUM(Forecast!D54:H54) -> 23727.491 | D29: =B29-C29 -> 0 | E29: 0.01 | F29: =IF(ABS(D29)<=E29,"OK","CHECK") -> OK | G29: DCF links correctly
A30: Guidance breaches in forecast (count) | B30: =COUNTIF(Forecast!D59:H61,"OUTSIDE")+COUNTIF(Forecast!D59:H61,"NO") -> 0 | C30: 0 | D30: =B30-C30 -> 0 | E30: 0 | F30: =IF(ABS(D30)<=E30,"OK","CHECK") -> OK | G30: Forecast stays inside stated guidance
A31: Target price = FY28E EPS × P/E | B31: =Valuation!B41 -> 2730 | C31: =ROUND(Forecast!E37*Assumptions!B32,-1) -> 2730 | D31: =B31-C31 -> 0 | E31: 0 | F31: =IF(ABS(D31)<=E31,"OK","CHECK") -> OK | G31: Valuation links
A32: FY26 dividend payout vs 60% policy | B32: ='Cash Flow'!E20 -> 0.60948582 | C32: 0.6 | D32: =B32-C32 -> 0.0094858156 | E32: 0.02 | F32: =IF(ABS(D32)<=E32,"OK","CHECK") -> OK | G32: Company pays 60% of profit before exceptionals; reported-EPS basis gives ~61%
A34: Checks passing or explained | B34: =COUNTIF(F5:F32,"OK")+COUNTIF(F5:F32,"EXPLAINED")&" of "&(COUNTA(F5:F32)) -> 26 of 26

Sheet Sources
A1: Source Log — every major number traced to a document
A2: Page = printed page from the PDF extract (confirm against the physical page). Type: PRIMARY = company filing · COMPETITOR = other company's disclosure · AGGREGATOR / MEDIA / BROKER = secondary
A4: # | B4: Metric | C4: Period | D4: Value used | E4: Source document | F4: Page | G4: Source type | H4: Verified | I4: URL / note
A5: 1 | B5: Revenue from operations | C5: FY25–26 | D5: 35,583.54 / 33,905.62 | E5: IAR FY26 — Consolidated P&L | F5: 461 | G5: PRIMARY | H5: Yes | I5: https://static.asianpaints.com/content/dam/annual-report-2526/pdf/Consolidated.pdf
A6: 2 | B6: Revenue from operations | C6: FY24 | D6: 35,494.73 | E6: IAR FY25 — Consolidated P&L | F6: 442 | G6: PRIMARY | H6: Yes | I6: https://static.asianpaints.com/content/dam/annual-folder-2425/pdf/Consolidated.pdf
A7: 3 | B7: Revenue, material cost, EBITDA, PBT, PAT, EPS | C7: FY17–26 | D7: Ten-year series | E7: IAR FY26 — Ten-Year Review | F7: 78–79 | G7: PRIMARY | H7: Yes | I7: https://static.asianpaints.com/content/dam/annual-report-2526/pdf/Ten-year-review.pdf
A8: 4 | B8: Cost lines (materials, employee, other) | C8: FY24–26 | D8: See Historicals | E8: IAR FY26 / FY25 — Consolidated P&L | F8: 461 / 442 | G8: PRIMARY | H8: Yes | I8: https://static.asianpaints.com/content/dam/annual-report-2526/pdf/Consolidated.pdf
A9: 5 | B9: Cost lines split | C9: FY23 | D9: See Historicals | E9: MarketsMojo (totals verified vs Ten-Year Review) | F9: — | G9: AGGREGATOR | H9: Partial | I9: Verify split in IAR FY24 consolidated P&L
A10: 6 | B10: Exceptional items | C10: FY25–26 | D10: (363.10) / (157.61) | E10: IAR FY26 — Consolidated P&L, Note 40 | F10: 461 | G10: PRIMARY | H10: Yes | I10: https://static.asianpaints.com/content/dam/annual-report-2526/pdf/Consolidated.pdf
A11: 7 | B11: Basic EPS | C11: FY24–26 | D11: 56.95 / 38.25 / 45.12 | E11: IAR FY26 / FY25 — Consolidated P&L | F11: 461 / 443 | G11: PRIMARY | H11: Yes | I11: v1 used 45.09 (aggregator) — corrected
A12: 8 | B12: Segment revenue (Deco & home décor, International, Industrial) | C12: FY25–26 | D12: 30,830.4 / 3,353.6 / 1,332.4 | E12: IAR FY26 — Financial Review (MD&A) | F12: 60–61 | G12: PRIMARY | H12: Yes | I12: https://static.asianpaints.com/content/dam/annual-report-2526/pdf/Financial-review.pdf
A13: 9 | B13: Standalone net sales, EBITDA, PAT | C13: FY22–26 | D13: See Historicals | E13: IAR FY26 — Financial Review / Ten-Year Review | F13: 60–63 / 78 | G13: PRIMARY | H13: Yes | I13: https://static.asianpaints.com/content/dam/annual-report-2526/pdf/Financial-review.pdf
A14: 10 | B14: Equity, NCI, borrowings, leases, payables, investments, inventory, receivables, cash, total assets | C14: FY25–26 | D14: See Balance Sheet | E14: IAR FY26 — Consolidated Balance Sheet | F14: 459 | G14: PRIMARY | H14: Yes | I14: https://static.asianpaints.com/content/dam/annual-report-2526/pdf/Consolidated.pdf
A15: 11 | B15: Same balance sheet items | C15: FY24 | D15: See Balance Sheet | E15: IAR FY25 — Consolidated Balance Sheet | F15: 440 | G15: PRIMARY | H15: Yes | I15: https://static.asianpaints.com/content/dam/annual-folder-2425/pdf/Consolidated.pdf
A16: 12 | B16: Borrowings and lease liabilities | C16: FY23 | D16: 972.21 / 960.41 | E16: IAR FY25 — Cash flow note (changes in financing liabilities) | F16: 448 | G16: PRIMARY | H16: Yes | I16: https://static.asianpaints.com/content/dam/annual-folder-2425/pdf/Consolidated.pdf
... A43: 39 | B43: Note 27 other expenses split (advertising, freight) | C43: FY26 | D43: NOT EXTRACTED | E43: IAR FY26 — Consolidated notes | F43: — | G43: PRIMARY | H43: No | I43: To do: extract to split 'other expenses' into A&P vs freight vs others
